Workbook
Name INTERVENIDAS: #REF!
Name Resumen: #REF!
Name SegmentaciónDeDatos_EPS_intervenida: #N/A
Name SegmentaciónDeDatos_EPS_intervenida1: #N/A
Name SegmentaciónDeDatos_MES: #N/A

Sheet Resumen General x Edades
A1: 1 | B1: 2 | C1: 3 | D1: 4 | E1: 5 | F1: 6 | G1: 7
A3: Resumen Incapacidades año - mes
A6: Año novedad | C6: Mes Novedad | D6: Incapacidades - Cuenta por cobrar a la EPS | E6: Reintegro Eps | F6: Castigo Cartera | G6: Pendiente de Recuperación Real | I6: Dinámica
A7: 2021 | B7: 1 | C7: ene | D7: 228677850 | E7: 206812943 | F7: =21615842+249065 -> 21864907 | G7: =+D7-E7-F7 -> 0 | H7: =IFERROR(VLOOKUP(C7,I:J,2,0),0) -> 0 | K7: =+E7+H7 -> 206812943
A8: 2021 | B8: 2 | C8: Feb | D8: 167318433 | E8: 143733285 | F8: 23585148 | G8: =+D8-E8-F8 -> 0 | H8: =IFERROR(VLOOKUP(C8,I:J,2,0),0) -> 0 | K8: =+E8+H8 -> 143733285
A9: 2021 | B9: 3 | C9: Mar | D9: 139015532 | E9: 117354941 | F9: 21660591 | G9: =+D9-E9-F9 -> 0 | H9: =IFERROR(VLOOKUP(C9,I:J,2,0),0) -> 0 | K9: =+E9+H9 -> 117354941
A10: 2021 | B10: 4 | C10: Abr | D10: 138688483 | E10: 119506087 | F10: 19182396 | G10: =+D10-E10-F10 -> 0 | H10: =IFERROR(VLOOKUP(C10,I:J,2,0),0) -> 0 | K10: =+E10+H10 -> 119506087
A11: 2021 | B11: 5 | C11: May | D11: 155175611 | E11: 155175611 | G11: =+D11-E11-F11 -> 0 | H11: =IFERROR(VLOOKUP(C11,I:J,2,0),0) -> 0 | K11: =+E11+H11 -> 155175611
A12: 2021 | B12: 6 | C12: Jun | D12: 181387641 | E12: 181387641 | G12: =+D12-E12-F12 -> 0 | H12: =IFERROR(VLOOKUP(C12,I:J,2,0),0) -> 0 | K12: =+E12+H12 -> 181387641
A13: 2021 | B13: 7 | C13: Jul | D13: 194630191 | E13: 194630191 | G13: =+D13-E13-F13 -> 0 | H13: =IFERROR(VLOOKUP(C13,I:J,2,0),0) -> 0 | K13: =+E13+H13 -> 194630191
A14: 2021 | B14: 8 | C14: Ago | D14: 203817326 | E14: =199274165+1780520 -> 201054685 | H14: =IFERROR(VLOOKUP(C14,I:J,2,0),0) -> 0 | K14: =+E14+H14 -> 201054685
A15: 2021 | B15: 9 | C15: Sep | D15: 188755821 | E15: 140727323 | H15: =IFERROR(VLOOKUP(C15,I:J,2,0),0) -> 0 | K15: =+E15+H15 -> 140727323
A16: 2021 | B16: 10 | C16: Oct | D16: 171425593 | E16: 113790868 | F16: 139549274 | H16: =IFERROR(VLOOKUP(C16,I:J,2,0),0) -> 0 | K16: =+E16+H16 -> 113790868
A17: 2021 | B17: 11 | C17: Nov | D17: 174728669 | E17: 90399180 | K17: =+E17+H17 -> 90399180
A18: 2021 | B18: 12 | C18: Dic | D18: 203843172 | E18: =185721080+90853 -> 185811933 | F18: 71237318 | G18: 0 | H18: =IFERROR(VLOOKUP(C18,I:J,2,0),0) -> 0 | K18: =+E18+H18 -> 185811933
A19: Total 2021 | D19: =SUM(D7:D18) -> 2147464322 | E19: =SUM(E7:E18) -> 1850384688 | F19: =SUM(F7:F18) -> 297079634 | G19: =SUM(G7:G18) -> 0 | K19: =+E19+H19 -> 1850384688
A20: 2022 | B20: 1 | C20: ene | D20: 212488754 | E20: 196361758 | F20: 16335861 | H20: =IFERROR(VLOOKUP(C20,I:J,2,0),0) -> 0 | K20: =+E20+H20 -> 196361758
A21: 2022 | B21: 2 | C21: Feb | D21: 198437111 | E21: 131882859 | F21: 66554252 | G21: =+D21-E21-F21 -> 0 | H21: =IFERROR(VLOOKUP(C21,I:J,2,0),0) -> 0 | K21: =+E21+H21 -> 131882859
A22: 2022 | B22: 3 | C22: Mar | D22: 177775379 | E22: 112397016 | F22: 65378363 | G22: =+D22-E22-F22 -> 0 | H22: =IFERROR(VLOOKUP(C22,I:J,2,0),0) -> 0 | K22: =+E22+H22 -> 112397016
A23: 2022 | B23: 4 | C23: Abr | D23: 181086022 | E23: 160796986 | F23: 20289036 | G23: =+D23-E23-F23 -> 0 | H23: =IFERROR(VLOOKUP(C23,I:J,2,0),0) -> 0 | K23: =+E23+H23 -> 160796986
A24: 2022 | B24: 5 | C24: May | D24: 163409172 | E24: 105397211 | F24: 16106923 | G24: =+D24-E24-F24 -> 41905038 | H24: =IFERROR(VLOOKUP(C24,I:J,2,0),0) -> 0 | K24: =+E24+H24 -> 105397211
A25: 2022 | B25: 6 | C25: Jun | D25: 164138948 | E25: 164504464 | G25: 242272 | H25: =IFERROR(VLOOKUP(C25,I:J,2,0),0) -> 0 | K25: =+E25+H25 -> 164504464
A26: 2022 | B26: 7 | C26: Jul | D26: 159004265 | E26: 159004265 | G26: =+D26-E26-F26 -> 0 | H26: =IFERROR(VLOOKUP(C26,I:J,2,0),0) -> 0 | K26: =+E26+H26 -> 159004265
A27: 2022 | B27: 8 | C27: Ago | D27: 184132744 | E27: 179271571 | G27: =+D27-E27-F27 -> 4861173 | H27: =IFERROR(VLOOKUP(C27,I:J,2,0),0) -> 0 | K27: =+E27+H27 -> 179271571
A28: 2022 | B28: 9 | C28: Sep | D28: 191941491 | E28: 160653276 | G28: =+D28-E28-F28 -> 31288215 | H28: =IFERROR(VLOOKUP(C28,I:J,2,0),0) -> 0 | K28: =+E28+H28 -> 160653276
A29: 2022 | B29: 10 | C29: Oct | D29: 189131114 | E29: 142101245 | G29: =+D29-E29-F29 -> 47029869 | H29: =IFERROR(VLOOKUP(C29,I:J,2,0),0) -> 0 | K29: =+E29+H29 -> 142101245
A30: 2022 | B30: 11 | C30: Nov | D30: 185604400 | E30: 185604400 | G30: =+D30-E30-F30 -> 0 | H30: =IFERROR(VLOOKUP(C30,I:J,2,0),0) -> 0 | K30: =+E30+H30 -> 185604400
A31: 2022 | B31: 12 | C31: Dic | D31: 174083427 | E31: 153199681 | G31: =+D31-E31-F31 -> 20883746 | H31: =IFERROR(VLOOKUP(C31,I:J,2,0),0) -> 0 | K31: =+E31+H31 -> 153199681
A32: Total 2022 | D32: =SUM(D20:D31) -> 2181232827 | E32: =SUM(E20:E31) -> 1851174732 | F32: =SUM(F20:F31) -> 184664435 | G32: =SUM(G20:G31) -> 146210313 | K32: =+E32+H32 -> 1851174732
A33: 2023 | B33: 1 | C33: ene | D33: 167819373 | E33: 167819373 | G33: =+D33-E33-F33 -> 0 | H33: =IFERROR(VLOOKUP(C33,I:J,2,0),0) -> 0 | K33: =+E33+H33 -> 167819373
A34: 2023 | B34: 2 | C34: Feb | D34: 231383519 | E34: 190108513 | G34: =+D34-E34-F34 -> 41275006 | H34: =IFERROR(VLOOKUP(C34,I:J,2,0),0) -> 0 | K34: =+E34+H34 -> 190108513
A35: 2023 | B35: 3 | C35: Mar | D35: 229546462 | E35: 224985751 | G35: =+D35-E35-F35 -> 4560711 | H35: =IFERROR(VLOOKUP(C35,I:J,2,0),0) -> 0 | K35: =+E35+H35 -> 224985751
A36: 2023 | B36: 4 | C36: Abr | D36: 212201656 | E36: 172164072 | G36: =+D36-E36-F36 -> 40037584 | H36: =IFERROR(VLOOKUP(C36,I:J,2,0),0) -> 0 | K36: =+E36+H36 -> 172164072
A37: 2023 | B37: 5 | C37: May | D37: 193403835 | E37: 165824586 | G37: =+D37-E37-F37 -> 27579249 | H37: =IFERROR(VLOOKUP(C37,I:J,2,0),0) -> 0 | K37: =+E37+H37 -> 165824586
A38: 2023 | B38: 6 | C38: Jun | D38: 226660411 | E38: 155108412 | G38: =+D38-E38-F38 -> 71551999 | H38: =IFERROR(VLOOKUP(C38,I:J,2,0),0) -> 0 | K38: =+E38+H38 -> 155108412
A39: 2023 | B39: 7 | C39: Jul | D39: 245907751 | E39: 245907751 | G39: =+D39-E39-F39 -> 0 | H39: =IFERROR(VLOOKUP(C39,I:J,2,0),0) -> 0 | K39: =+E39+H39 -> 245907751
A40: 2023 | B40: 8 | C40: Ago | D40: 208099142 | E40: 191348765 | G40: =+D40-E40-F40 -> 16750377 | H40: =IFERROR(VLOOKUP(C40,I:J,2,0),0) -> 0 | K40: =+E40+H40 -> 191348765
A41: 2023 | B41: 9 | C41: Sep | D41: 206599433 | E41: 206599433 | G41: =+D41-E41-F41 -> 0 | H41: =IFERROR(VLOOKUP(C41,I:J,2,0),0) -> 0 | K41: =+E41+H41 -> 206599433
A42: 2023 | B42: 10 | C42: Oct | D42: 194176254 | E42: 190780768 | G42: =+D42-E42-F42 -> 3395486 | H42: =IFERROR(VLOOKUP(C42,I:J,2,0),0) -> 0 | K42: =+E42+H42 -> 190780768
A43: 2023 | B43: 11 | C43: Nov | D43: 179386564 | E43: 135185437 | G43: =+D43-E43-F43 -> 44201127 | H43: =IFERROR(VLOOKUP(C43,I:J,2,0),0) -> 0 | K43: =+E43+H43 -> 135185437
A44: 2023 | B44: 12 | C44: Dic | D44: 162052068 | E44: 75617395 | G44: =+D44-E44-F44 -> 86434673 | H44: =IFERROR(VLOOKUP(C44,I:J,2,0),0) -> 0 | K44: =+E44+H44 -> 75617395
A45: Total 2023 | D45: =SUM(D33:D44) -> 2457236468 | E45: =SUM(E33:E44) -> 2121450256 | F45: =SUM(F33:F44) -> 0 | G45: =SUM(G33:G44) -> 335786212 | K45: =+E45+H45 -> 2121450256
A46: 2024 | B46: 1 | C46: ene | D46: 192806559 | E46: 160153993 | G46: =+D46-E46-F46 -> 32652566 | H46: =IFERROR(VLOOKUP(C46,I:J,2,0),0) -> 0 | K46: =+E46+H46 -> 160153993
A47: 2024 | B47: 2 | C47: Feb | D47: 194880042 | E47: 131710556 | G47: =+D47-E47-F47 -> 63169486 | H47: =IFERROR(VLOOKUP(C47,I:J,2,0),0) -> 0 | K47: =+E47+H47 -> 131710556
A48: 2024 | B48: 3 | C48: Mar | D48: 180005716 | E48: 175223332 | G48: =+D48-E48-F48 -> 4782384 | H48: =IFERROR(VLOOKUP(C48,I:J,2,0),0) -> 0 | K48: =+E48+H48 -> 175223332
A49: 2024 | B49: 4 | C49: Abr | D49: 174085604 | E49: 174085604 | G49: =+D49-E49-F49 -> 0 | H49: =IFERROR(VLOOKUP(C49,I:J,2,0),0) -> 0 | K49: =+E49+H49 -> 174085604
A50: 2024 | B50: 5 | C50: May | D50: 211340362 | E50: 112338228 | G50: =+D50-E50-F50 -> 99002134 | H50: =IFERROR(VLOOKUP(C50,I:J,2,0),0) -> 0 | K50: =+E50+H50 -> 112338228
A51: 2024 | B51: 6 | C51: Jun | D51: 217237506 | E51: 112502344 | G51: =+D51-E51-F51 -> 104735162 | H51: =IFERROR(VLOOKUP(C51,I:J,2,0),0) -> 0 | K51: =+E51+H51 -> 112502344
A52: 2024 | B52: 7 | C52: Jul | D52: 204350015 | E52: 131040461 | G52: =+D52-E52-F52 -> 73309554 | H52: =IFERROR(VLOOKUP(C52,I:J,2,0),0) -> 0 | K52: =+E52+H52 -> 131040461
A53: 2024 | B53: 8 | C53: Ago | D53: 256131617 | E53: 239873148 | G53: =+D53-E53-F53 -> 16258469 | H53: =IFERROR(VLOOKUP(C53,I:J,2,0),0) -> 0 | K53: =+E53+H53 -> 239873148
A54: 2024 | B54: 9 | C54: Sep | D54: 189273422 | E54: 69573399 | G54: =+D54-E54-F54 -> 119700023 | H54: =IFERROR(VLOOKUP(C54,I:J,2,0),0) -> 0 | K54: =+E54+H54 -> 69573399
A55: 2024 | B55: 10 | C55: Oct | D55: 206352915 | E55: 206352915 | G55: =+D55-E55-F55 -> 0 | H55: =IFERROR(VLOOKUP(C55,I:J,2,0),0) -> 0 | K55: =+E55+H55 -> 206352915
A56: 2024 | B56: 11 | C56: Nov | D56: 241122278 | E56: 241122278 | G56: =+D56-E56-F56 -> 0 | H56: =IFERROR(VLOOKUP(C56,I:J,2,0),0) -> 0 | K56: =+E56+H56 -> 241122278
A57: 2024 | B57: 12 | C57: Dic | D57: 224626908 | E57: 224626908 | G57: =+D57-E57-F57 -> 0 | H57: =IFERROR(VLOOKUP(C57,I:J,2,0),0) -> 0 | K57: =+E57+H57 -> 224626908
A58: Total 2024 | D58: =SUM(D46:D57) -> 2492212944 | E58: =SUM(E46:E57) -> 1978603166 | F58: =SUM(F46:F57) -> 0 | G58: =SUM(G46:G57) -> 513609778 | H58: =IFERROR(VLOOKUP(C58,I:J,2,0),0) -> 0 | K58: =+E58+H58 -> 1978603166
A59: 2025 | B59: 1 | C59: ene | D59: 262139144 | E59: 199523475 | G59: =+D59-E59-F59 -> 62615669 | H59: =IFERROR(VLOOKUP(C59,I:J,2,0),0) -> 0 | K59: =+E59+H59 -> 199523475
A60: 2025 | B60: 2 | C60: Feb | D60: 298312397 | E60: 229670860 | G60: =+D60-E60-F60 -> 68641537 | H60: =IFERROR(VLOOKUP(C60,I:J,2,0),0) -> 0 | K60: =+E60+H60 -> 229670860
A61: 2025 | B61: 3 | C61: Mar | D61: 239533077 | E61: 164291959 | G61: =+D61-E61-F61 -> 75241118 | H61: =IFERROR(VLOOKUP(C61,I:J,2,0),0) -> 0 | K61: =+E61+H61 -> 164291959
A62: 2025 | B62: 4 | C62: Abr | D62: 260363532 | E62: 200532114 | G62: =+D62-E62-F62 -> 59831418 | H62: =IFERROR(VLOOKUP(C62,I:J,2,0),0) -> 0 | K62: =+E62+H62 -> 200532114
A63: 2025 | B63: 5 | C63: May | D63: 252838984 | E63: 200850938 | G63: =+D63-E63-F63 -> 51988046 | H63: =IFERROR(VLOOKUP(C63,I:J,2,0),0) -> 0 | K63: =+E63+H63 -> 200850938
A64: 2025 | B64: 6 | C64: Jun | D64: 259312318 | E64: 222392952 | G64: =+D64-E64-F64 -> 36919366 | H64: =IFERROR(VLOOKUP(C64,I:J,2,0),0) -> 0 | K64: =+E64+H64 -> 222392952
A65: 2025 | B65: 7 | C65: Jul | D65: 225693925 | E65: 225693925 | G65: =+D65-E65-F65 -> 0 | H65: =IFERROR(VLOOKUP(C65,I:J,2,0),0) -> 0 | K65: =+E65+H65 -> 225693925
A66: 2025 | B66: 8 | C66: Ago | D66: 214873495 | E66: 165140732 | G66: =+D66-E66-F66 -> 49732763 | H66: =IFERROR(VLOOKUP(C66,I:J,2,0),0) -> 0 | K66: =+E66+H66 -> 165140732
A67: 2025 | B67: 9 | C67: Sep | D67: 257632349 | E67: 187761138 | G67: =+D67-E67-F67 -> 69871211 | H67: =IFERROR(VLOOKUP(C67,I:J,2,0),0) -> 0 | K67: =+E67+H67 -> 187761138
A68: 2025 | B68: 10 | C68: Oct | E68: 3260742 | G68: =+D68-E68-F68 -> -3260742 | H68: =IFERROR(VLOOKUP(C68,I:J,2,0),0) -> 0 | K68: =+E68+H68 -> 3260742
A69: 2025 | B69: 11 | C69: Nov | E69: 0 | G69: =+D69-E69-F69 -> 0 | H69: =IFERROR(VLOOKUP(C69,I:J,2,0),0) -> 0 | K69: =+E69+H69 -> 0
A70: 2025 | B70: 12 | C70: Dic | E70: 0 | G70: =+D70-E70-F70 -> 0 | H70: =IFERROR(VLOOKUP(C70,I:J,2,0),0) -> 0 | K70: =+E70+H70 -> 0
A71: Total 2025 | D71: =SUM(D59:D70) -> 2270699221 | E71: =SUM(E59:E70) -> 1799118835 | F71: =SUM(F59:F70) -> 0 | G71: =SUM(G59:G70) -> 471580386
A72: Total general | B72: Total general | C72: Total general | D72: =+D19+D32+D45+D58+D71 -> 11548845782 | E72: =+E19+E32+E45+E58+E71 -> 9600731677 | F72: =+F19+F32+F45+F58+F71 -> 481744069 | G72: =+G19+G32+G45+G58+G71 -> 1467186689 | H72: =E72+F72 -> 10082475746
J73: Conciliacion 1 | M73: Conciliacion 2
F74: Sáldo nómina | G74: =+G72 -> 1467186689 | J74: saldo inicial | K74: 1450984915 | M74: PAGOS MES | N74: =-K76 -> -295802141
F75: Saldo Contable | G75: =K77 -> 1412815123 | J75: Causado | K75: 257632349 | M75: PAGOS GI | N75: 295151842
F76: Partidas reg sin identificar | G76: =-SUM(E85:E114) -> -54371566 | J76: pagos | K76: 295802141 | M76: PAGOS PENDIENTES MES | N76: 237250
F77: Incapacidades sin registrar | G77: 0 | J77: saldo mes | K77: =K74+K75-K76 -> 1412815123 | M77: PAGOS PENDIENTES MES | N77: 33449
F78: DIFERENCIA | G78: =+G74-G75+G76-G77 -> 0 | J78: Saldo confirmado Cont | K78: 1407315011 | M78: PAGOS PENDIENTES MES | N78: 47450
J79: Dif | K79: =+K77-K78 -> 5500112 | M79: PAGOS PENDIENTES MES | N79: 332150
M80: Dif siempre 0 | N80: =SUM(N74:N79) -> 0
D84: Fondo/Mes | E84: Valor | F84: Fecha | G84: Observacion
D85: CAPRESOCA | E85: 5460000 | F85: 45689
D86: COLPATRIA ARP | E86: 13302223 | F86: 45200
D87: COLPATRIA ARP | E87: 3573000 | F87: 45261 | I87: 257632349 | J87: 187761138
D88: COLPATRIA ARP | E88: 57177 | F88: 45747 | J88: 2686361
D89: COLPATRIA ARP | E89: 256234 | F89: enero
D90: COMPENSAR | E90: 9037356 | F90: 45170
D91: COOSALUD EPS | E91: 580000 | F91: 45687
D92: COOSALUD EPS | E92: 696000 | F92: 45352
D93: COOSALUD EPS | E93: 1237334 | F93: 45261
D94: EMPRESAS PUBLICAS DE MEDELLIN DEPARTAMENTO MEDICO | E94: 41238 | F94: 45758 | G94: occi
D95: EMPRESAS PUBLICAS DE MEDELLIN DEPARTAMENTO MEDICO | E95: 630385 | F95: 45597 | G95: Conciliacion Yen
D96: EMPRESAS PUBLICAS DE MEDELLIN DEPARTAMENTO MEDICO | E96: 33449 | F96: 45715 | G96: occi
D97: EMPRESAS PUBLICAS DE MEDELLIN DEPARTAMENTO MEDICO | E97: 1340320 | F97: 45200
D98: FAMISANAR | E98: 37819 | F98: 45597
D99: FAMISANAR | E99: 11152100 | F99: 45200
D100: NUEVA E.P.S. | E100: 650000 | F100: 45597
D101: NUEVA E.P.S. | E101: 88951 | F101: 45627
D102: S.O.S | E102: 77334 | F102: 45352
D103: SANITAS | E103: 866667 | F103: 45658
D104: SANITAS | E104: 3476318 | F104: 45352
D105: SANITAS | E105: 1037794 | F105: 45444
D106: SAVIA SALUD - AMA | E106: 123017 | F106: 45658
...

Sheet PROVISION
A4: Provisión Incapacidades por Edades
U5: 67952700
A8: Año | B8: Total Incapacidades | C8: Valores Recuperados | E8: Pendiente por Recuperar | G8: No cobrables en resultados - CASTIGO | H8: SALDO DIC 2024 | I8: Saldo CXC Enero 2025 | J8: Saldo CXC Febrero 2025 | K8: Saldo CXC Marzo 2025 | L8: Saldo CXC Abril 2025 | M8: Saldo CXC Mayo 2025 | N8: Saldo CXC Junio 2025 | O8: Saldo CXC Julio 2025 | P8: Saldo CXC Agosto 2025 | Q8: Saldo CXC Septiembre 2025 | R8: Provision Actual | S8: Exceso/ Faltante | T8: % Provision | U8: Promedio provisiones
A9: Total 2021 | B9: =+VLOOKUP(A9,'Resumen General x Edades'!A:D,4,0) -> 2147464322 | C9: =+VLOOKUP(A9,'Resumen General x Edades'!A:E,5,0) -> 1850384688 | D9: =+C9/B9 -> 0.86166027 | E9: =ROUND(B9-C9-G9,0) -> 0 | F9: =+E9/B9 -> 0 | G9: =+VLOOKUP(A9,'Resumen General x Edades'!A:F,6,0) -> 297079634 | H9: 71570443 | I9: 71479590 | J9: 71479590 | K9: 71479590 | L9: 71479590 | M9: 71479590 | N9: 0 | O9: 0 | P9: 0 | Q9: =+VLOOKUP(A9,'Resumen General x Edades'!A:G,7,0) -> 0 | R9: =791949000-17136000+9942000-3767000-159220461-3382087+68166000+69889000+68055000-139549286+126271000+143456200+139702100+186775000+67952700-9294200-184664435+3549300-51783100+79087000-27808600+35066500-15550700+4874100+M23+M22 -> 1153905731 | S9: =SUM(Q9:Q13)-R9 -> 313280958 | T9: =R14/Q14 -> 0.78647505 | U9: =SUM(Q9:Q13)/SUM(B9:B12) -> 0.1581336
A10: Total 2022 | B10: =+VLOOKUP(A10,'Resumen General x Edades'!A:D,4,0) -> 2181232827 | C10: =+VLOOKUP(A10,'Resumen General x Edades'!A:E,5,0) -> 1851174732 | D10: =+C10/B10 -> 0.84868278 | E10: =ROUND(B10-C10-G10,0) -> 145393660 | F10: =+E10/B10 -> 0.066656644 | G10: =+VLOOKUP(A10,'Resumen General x Edades'!A:F,6,0) -> 184664435 | H10: 158295669 | I10: 158295669 | J10: 158295669 | K10: 158295669 | L10: 155995669 | M10: 155962336 | N10: 156204608 | O10: 156204608 | P10: 156204608 | Q10: =+VLOOKUP(A10,'Resumen General x Edades'!A:G,7,0) -> 146210313
A11: Total 2023 | B11: =+VLOOKUP(A11,'Resumen General x Edades'!A:D,4,0) -> 2457236468 | C11: =+VLOOKUP(A11,'Resumen General x Edades'!A:E,5,0) -> 2121450256 | D11: =+C11/B11 -> 0.86334803 | E11: =ROUND(B11-C11-G11,0) -> 335786212 | F11: =+E11/B11 -> 0.13665197 | G11: =+VLOOKUP(A11,'Resumen General x Edades'!A:F,6,0) -> 0 | H11: 346716753 | I11: 346678086 | J11: 346678086 | K11: 346678086 | L11: 346400753 | M11: 345898086 | N11: 345845374 | O11: 345285528 | P11: 345218862 | Q11: =+VLOOKUP(A11,'Resumen General x Edades'!A:G,7,0) -> 335786212
A12: Total 2024 | B12: =+VLOOKUP(A12,'Resumen General x Edades'!A:D,4,0) -> 2492212944 | C12: =+VLOOKUP(A12,'Resumen General x Edades'!A:E,5,0) -> 1978603166 | D12: =+C12/B12 -> 0.79391417 | E12: =ROUND(B12-C12-G12,0) -> 513609778 | F12: =+E12/B12 -> 0.20608583 | G12: =+VLOOKUP(A12,'Resumen General x Edades'!A:F,6,0) -> 0 | H12: 941244958 | I12: 663839347 | J12: 626002165 | K12: 555207618 | L12: 543285700 | M12: 508882153 | N12: 505759412 | O12: 503279717 | P12: 500376959 | Q12: =+VLOOKUP(A12,'Resumen General x Edades'!A:G,7,0) -> 513609778
A13: Total 2025 | B13: =+VLOOKUP(A13,'Resumen General x Edades'!A:D,4,0) -> 2270699221 | C13: =+VLOOKUP(A13,'Resumen General x Edades'!A:E,5,0) -> 1799118835 | D13: =+C13/B13 -> 0.79231931 | E13: =ROUND(B13-C13-G13,0) -> 471580386 | F13: =+E13/B13 -> 0.20768069 | G13: =+VLOOKUP(A13,'Resumen General x Edades'!A:F,6,0) -> 0 | H13: 0 | I13: 237017178 | J13: 445942269 | K13: 513714245 | L13: 647887465 | M13: 666062207 | N13: 674640011 | O13: 609047351 | P13: 701052617 | Q13: =+VLOOKUP(A13,'Resumen General x Edades'!A:G,7,0) -> 471580386
A14: Totales | B14: =SUM(B9:B13) -> 11548845782 | C14: =SUM(C9:C13) -> 9600731677 | D14: =SUM(D9:D13) -> 4.1599245 | E14: =SUM(E9:E13) -> 1466370036 | F14: =SUM(F9:F13) -> 0.61707514 | G14: =SUM(G9:G13) -> 481744069 | H14: =SUM(H9:H13) -> 1517827823 | I14: 1477309870 | J14: =SUM(J9:J13) -> 1648397779 | K14: 1645375208 | L14: 1765049177 | M14: 1748284372 | N14: =SUM(N9:N13) -> 1682449405 | O14: =SUM(O9:O13) -> 1613817204 | P14: =SUM(P9:P13) -> 1702853046 | Q14: =SUM(Q9:Q13) -> 1467186689 | R14: =SUM(R9:R13) -> 1153905731 | S14: =SUM(S9:S13) -> 313280958 | T14: =SUM(T9:T13) -> 0.78647505 | U14: =SUM(U9:U13) -> 0.1581336
I19: Conciliacion mes | L19: Histórico Faltante Provision
I21: item | J21: Valor | L21: Mes | M21: Valor
I22: Sáldo nómina | J22: ='Resumen General x Edades'!G74 -> 1467186689 | L22: 45901 | M22: 34809200
I23: Saldo Contable | J23: ='Resumen General x Edades'!G75 -> 1412815123 | L23: 45870 | M23: -63482500
I24: Partidas reg. sin identificar | J24: ='Resumen General x Edades'!G76-'Resumen General x Edades'!G77 -> -54371566 | L24: 45839 | M24: 4874100
I25: Diferencia | J25: =+J22-J23+J24 -> 0 | L25: 45809 | M25: =+'Nuevo Modelo2'!I84 -> -15550700
L26: 45778 | M26: 35066500
L27: 45748 | M27: -27808600
L28: 45717 | M28: 79087000
L29: 45689 | M29: -51783100
L30: 45658 | M30: 3549300

Sheet Nuevo Modelo2
A2: MODELO INICIAL (3 CRITERIOS)
A3: 1. MODELO DE PROVISIÓN SALDO GENERAL | H3: Prov. Actual | I3: =+PROVISION!R9 -> 1153905731
A4: MODELO ECL 2025 | H4: Pérdida con Modelo | I4: Disminicion Prov mes a mes
A5: Total Cartera | B5: =SUM(B6:B11) -> 404454216
A6: 0-180 | B6: 7910541 | C6: 0.36344208 | D6: =+B6*C6 -> 2875023.5 | G6: Enero | H6: 57831458 | I6: 1.1008624e+09
A7: 181-209 | B7: 263652526 | C7: 0.36344208 | D7: =+B7*C7 -> 95822422 | G7: Febrero | H7: 64430769 | I7: 1.04248e+09
A8: 210-239 | B8: 25384117 | C8: 0.36344208 | D8: =+B8*C8 -> 9225656.2 | G8: Marzo | H8: 61831570 | I8: 1.1241662e+09
A9: 240-269 | B9: 27161138 | C9: 0.36344208 | D9: =+B9*C9 -> 9871500.4 | G9: Abril | H9: 86838136 | I9: 1.0963576e+09
A10: 270-299 | B10: 31983583 | C10: 0.24229472 | D10: =+B10*C10 -> 7749453.2 | G10: Mayo | H10: 84014618 | I10: 1.1064175e+09
A11: 300 en adelante | B11: 48362311 | C11: 0.24229472 | D11: =+B11*C11 -> 11717933 | G11: Junio | H11: 85571038 | I11: 1.0936903e+09
A12: Total Provision | D12: =+SUM(D6:D11) -> 1.3726199e+08 | G12: Julio | H12: 77071845 | I12: 1.097008e+09
G13: Agosto | H13: 85527231 | I13: 1.0335693e+09
A14: 2. CARTERA MÁS DE UN AÑO Y MÁS DE 80 MILLONES -(Cartera por cobrar de más de 1 año desglosado por eps y por saldos mayores a 80 millones. (Sobre ese saldo mirar el % castigado y aplicar a la historia de pérdida) | G14: Septiembre | H14: =+D12 -> 1.3726199e+08 | I14: =+$I$3-H14 -> 1.0166437e+09
G15: Octubre | H15: =+D14 -> 0 | I15: =+$I$3-H15 -> 1153905731
G16: Noviembre | H16: =+D15 -> 0 | I16: =+$I$3-H16 -> 1153905731
A17: EPS | B17: Cartera más de un año | C17: % castigado | D17: Valor provisión | G17: Diciembre | H17: =+D16 -> 0 | I17: =+$I$3-H17 -> 1153905731
H19: RANGOS PARA MODELO ECL
H20: 0-180 | I20: En plazo
H21: 181-209 | I21: 0-30
H22: 210-239 | I22: 31-60
H23: 240-269 | I23: 61-90
A24: Total general | B24: =+SUM(B19:B23) -> 0 | D24: =+SUM(D19:D23) -> 0 | H24: 270-299 | I24: 91-180
H25: 300 en adelante | I25: Más de 180
A26: 3 criterio. Cartera por cobrar de más de 1 año desglosado por eps y por saldos menores a 80 millones y especial (Aquí van incluidas todas las eps de liquidación e intervención) Se les debe asignar porcentaje de castigo (90-100%) de acuerdo al movimientos de cada una.
A28: EPS | B28: Cartera más de un año | C28: % castigado | D28: Valor provisión | E28: INTERVENIDAS
A29: SANITAS | B29: =F29-IFERROR(VLOOKUP(A29,'Resumen General x Edades'!$D$118:$E$131,2,0),0) -> 345646332 | C29: 0.9 | D29: =+B29*C29 -> 3.110817e+08 | E29: =IFERROR(VLOOKUP(A29,$I$37:$I$49,1,0)," ") -> SANITAS | F29: 351027111
A30: EPS SURA (ANTES SUSALUD) | B30: =F30-IFERROR(VLOOKUP(A30,'Resumen General x Edades'!$D$118:$E$131,2,0),0) -> 216308538 | C30: 0.9 | D30: =+B30*C30 -> 1.9467768e+08 | E30: =IFERROR(VLOOKUP(A30,$I$37:$I$49,1,0)," ") -> EPS SURA (ANTES SUSALUD) | F30: 216308538
A31: SALUD TOTAL | B31: =F31-IFERROR(VLOOKUP(A31,'Resumen General x Edades'!$D$118:$E$131,2,0),0) -> 137964155 | C31: 0.9 | D31: =+B31*C31 -> 1.2416774e+08 | E31: =IFERROR(VLOOKUP(A31,$I$37:$I$49,1,0)," ") | F31: 137964155
A32: FAMISANAR | B32: =F32-IFERROR(VLOOKUP(A32,'Resumen General x Edades'!$D$118:$E$131,2,0),0) -> 143469868 | C32: 0.9 | D32: =+B32*C32 -> 1.2912288e+08 | E32: =IFERROR(VLOOKUP(A32,$I$37:$I$49,1,0)," ") -> FAMISANAR | F32: 154659787
A33: NUEVA E.P.S. | B33: =F33-IFERROR(VLOOKUP(A33,'Resumen General x Edades'!$D$118:$E$131,2,0),0) -> 121341879 | C33: 0.9 | D33: =+B33*C33 -> 1.0920769e+08 | E33: =IFERROR(VLOOKUP(A33,$I$37:$I$49,1,0)," ") -> NUEVA E.P.S. | F33: 122080830 | G33: 2216570
A34: COMPENSAR | B34: =F34-IFERROR(VLOOKUP(A34,'Resumen General x Edades'!$D$118:$E$131,2,0),0) -> 50850241 | C34: 0.9 | D34: =+B34*C34 -> 45765217 | E34: =IFERROR(VLOOKUP(A34,$I$37:$I$49,1,0)," ") -> COMPENSAR | F34: 59887597
A35: ALIANSALUD EPS (ANTES COLMEDICA) | B35: =F35-IFERROR(VLOOKUP(A35,'Resumen General x Edades'!$D$118:$E$131,2,0),0) -> 35755589 | C35: 0.9 | D35: =+B35*C35 -> 32180030 | E35: =IFERROR(VLOOKUP(A35,$I$37:$I$49,1,0)," ") | F35: 35755589
A36: S.O.S. SERVICIO OCCIDENTAL DE SALUD S.A. | B36: =F36-IFERROR(VLOOKUP(A36,'Resumen General x Edades'!$D$118:$E$131,2,0),0) -> 30665850 | C36: 0.9 | D36: =+B36*C36 -> 27599265 | E36: =IFERROR(VLOOKUP(A36,$I$37:$I$49,1,0)," ") | F36: 30665850
A37: COMFENALCO VALLE | B37: =F37-IFERROR(VLOOKUP(A37,'Resumen General x Edades'!$D$118:$E$131,2,0),0) -> 30084604 | C37: 0.9 | D37: =+B37*C37 -> 27076144 | E37: =IFERROR(VLOOKUP(A37,$I$37:$I$49,1,0)," ") | F37: 30464204 | H37: 8600669427 | I37: COMPENSAR
A38: MEDIMAS EPS | B38: =F38-IFERROR(VLOOKUP(A38,'Resumen General x Edades'!$D$118:$E$131,2,0),0) -> 19582331 | C38: 0.9 | D38: =+B38*C38 -> 17624098 | E38: =IFERROR(VLOOKUP(A38,$I$37:$I$49,1,0)," ") -> MEDIMAS EPS | F38: 19582331 | H38: 8140003371 | I38: EMSSANAR
A39: COOMEVA | B39: =F39-IFERROR(VLOOKUP(A39,'Resumen General x Edades'!$D$118:$E$131,2,0),0) -> 17814953 | C39: 0.9 | D39: =+B39*C39 -> 16033458 | E39: =IFERROR(VLOOKUP(A39,$I$37:$I$49,1,0)," ") -> COOMEVA | F39: 17814953 | H39: 8000887022 | I39: EPS SURA (ANTES SUSALUD)
A40: COLPATRIA ARP | B40: =F40-IFERROR(VLOOKUP(A40,'Resumen General x Edades'!$D$118:$E$131,2,0),0) -> -5489804 | C40: 0.9 | D40: =+B40*C40 -> -4940823.6 | E40: =IFERROR(VLOOKUP(A40,$I$37:$I$49,1,0)," ") | F40: 11698830 | H40: 8300035647 | I40: FAMISANAR
A41: FOSYGA | B41: =F41-IFERROR(VLOOKUP(A41,'Resumen General x Edades'!$D$118:$E$131,2,0),0) -> 8884331 | C41: 0.9 | D41: =+B41*C41 -> 7995897.9 | E41: =IFERROR(VLOOKUP(A41,$I$37:$I$49,1,0)," ") | F41: 8884331 | H41: 8002514406 | I41: SANITAS
A42: COOSALUD EPS | B42: =F42-IFERROR(VLOOKUP(A42,'Resumen General x Edades'!$D$118:$E$131,2,0),0) -> 7758609 | C42: 0.9 | D42: =+B42*C42 -> 6982748.1 | E42: =IFERROR(VLOOKUP(A42,$I$37:$I$49,1,0)," ") | F42: 10271943 | H42: 9001562642 | I42: NUEVA E.P.S.
A43: EMSSANAR | B43: =F43-IFERROR(VLOOKUP(A43,'Resumen General x Edades'!$D$118:$E$131,2,0),0) -> 8131800 | C43: 0.9 | D43: =+B43*C43 -> 7318620 | E43: =IFERROR(VLOOKUP(A43,$I$37:$I$49,1,0)," ") -> EMSSANAR | F43: 8131800 | I43: MEDIMAS EPS
A44: CAJACOPI ATLANTICO | B44: =F44-IFERROR(VLOOKUP(A44,'Resumen General x Edades'!$D$118:$E$131,2,0),0) -> 7007873 | C44: 0.9 | D44: =+B44*C44 -> 6307085.7 | E44: =IFERROR(VLOOKUP(A44,$I$37:$I$49,1,0)," ") | F44: 7007873 | I44: COOMEVA
A45: MUTUAL SER | B45: =F45-IFERROR(VLOOKUP(A45,'Resumen General x Edades'!$D$118:$E$131,2,0),0) -> 6653090 | C45: 0.9 | D45: =+B45*C45 -> 5987781 | E45: =IFERROR(VLOOKUP(A45,$I$37:$I$49,1,0)," ") | F45: 6653090
A46: CAPRESOCA | B46: =F46-IFERROR(VLOOKUP(A46,'Resumen General x Edades'!$D$118:$E$131,2,0),0) -> -975006 | C46: 0.9 | D46: =+B46*C46 -> -877505.4 | E46: =IFERROR(VLOOKUP(A46,$I$37:$I$49,1,0)," ") | F46: 4484994
A47: SALUD MIA EPS | B47: =F47-IFERROR(VLOOKUP(A47,'Resumen General x Edades'!$D$118:$E$131,2,0),0) -> 2022208 | C47: 0.9 | D47: =+B47*C47 -> 1819987.2 | E47: =IFERROR(VLOOKUP(A47,$I$37:$I$49,1,0)," ") | F47: 2022208
A48: CAPITAL SALUD | B48: =F48-IFERROR(VLOOKUP(A48,'Resumen General x Edades'!$D$118:$E$131,2,0),0) -> 1211961 | C48: 0.9 | D48: =+B48*C48 -> 1090764.9 | E48: =IFERROR(VLOOKUP(A48,$I$37:$I$49,1,0)," ") | F48: 1211961
A49: SAVIA SALUD | B49: =F49-IFERROR(VLOOKUP(A49,'Resumen General x Edades'!$D$118:$E$131,2,0),0) -> 799168 | C49: 0.9 | D49: =+B49*C49 -> 719251.2 | E49: =IFERROR(VLOOKUP(A49,$I$37:$I$49,1,0)," ") | F49: 799168
A50: COMFAORIENTE | B50: =F50-IFERROR(VLOOKUP(A50,'Resumen General x Edades'!$D$118:$E$131,2,0),0) -> 535711 | C50: 0.9 | D50: =+B50*C50 -> 482139.9 | E50: =IFERROR(VLOOKUP(A50,$I$37:$I$49,1,0)," ") | F50: 535711
A51: ASMET SALUD EPS SAS | B51: =F51-IFERROR(VLOOKUP(A51,'Resumen General x Edades'!$D$118:$E$131,2,0),0) -> 1381823 | C51: 0.9 | D51: =+B51*C51 -> 1243640.7 | E51: =IFERROR(VLOOKUP(A51,$I$37:$I$49,1,0)," ") | F51: 1381823
A52: COMFAMILIAR GUAJIRA | B52: =F52-IFERROR(VLOOKUP(A52,'Resumen General x Edades'!$D$118:$E$131,2,0),0) -> 358576 | C52: 0.9 | D52: =+B52*C52 -> 322718.4 | E52: =IFERROR(VLOOKUP(A52,$I$37:$I$49,1,0)," ") | F52: 358576
A53: COMPARTA | B53: =F53-IFERROR(VLOOKUP(A53,'Resumen General x Edades'!$D$118:$E$131,2,0),0) -> 213565 | C53: 0.9 | D53: =+B53*C53 -> 192208.5 | E53: =IFERROR(VLOOKUP(A53,$I$37:$I$49,1,0)," ") | F53: 213565
A54: EMPRESAS PUBLICAS DE MEDELLIN DEPARTAMENTO MEDICO | B54: =F54-IFERROR(VLOOKUP(A54,'Resumen General x Edades'!$D$118:$E$131,2,0),0) -> -1961520 | C54: 0.9 | D54: =+B54*C54 -> -1765368 | E54: =IFERROR(VLOOKUP(A54,$I$37:$I$49,1,0)," ") | F54: 83872
A55: EPS ECOOPSOS S.A.S | B55: =F55-IFERROR(VLOOKUP(A55,'Resumen General x Edades'!$D$118:$E$131,2,0),0) -> 50693 | C55: 0.9 | D55: =+B55*C55 -> 45623.7 | E55: =IFERROR(VLOOKUP(A55,$I$37:$I$49,1,0)," ") | F55: 50693
A56: DUSAKAWI | B56: =F56-IFERROR(VLOOKUP(A56,'Resumen General x Edades'!$D$118:$E$131,2,0),0) -> 39842 | C56: 0.9 | D56: =+B56*C56 -> 35857.8 | E56: =IFERROR(VLOOKUP(A56,$I$37:$I$49,1,0)," ") | F56: 39842
... A59: CONVIDA | B59: =F59-IFERROR(VLOOKUP(A59,'Resumen General x Edades'!$D$118:$E$131,2,0),0) -> 13281 | C59: 0.9 | D59: =+B59*C59 -> 11952.9 | E59: =IFERROR(VLOOKUP(A59,$I$37:$I$49,1,0)," ") | F59: 13281
A60: EPS MUTUAL SER | B60: =F60-IFERROR(VLOOKUP(A60,'Resumen General x Edades'!$D$118:$E$131,2,0),0) -> 2682804 | C60: 0.9 | D60: =+B60*C60 -> 2414523.6 | F60: 2682804
A61: COOSALUD MOVILIDAD | B61: =F61-IFERROR(VLOOKUP(A61,'Resumen General x Edades'!$D$118:$E$131,2,0),0) -> 536590 | C61: 0.9 | D61: =+B61*C61 -> 482931 | F61: 536590
A62: TOTAL GENERAL | B62: =+SUM(B29:B61) -> 1189395863 | D62: =+SUM(D29:D61) -> 1.0704563e+09 | F62: =+SUM(F29:F61) -> 1243329828 | G62: =+F62-B62 -> 53933965
C65: CRITERIO 1 | D65: =+D12 -> 1.3726199e+08
C66: CRITERIO 2 | D66: =+D24 -> 0
C67: CRITERIO 3 | D67: =+D62 -> 1.0704563e+09
C68: TOTAL PROVISIÓN MODELO PERDIDA ESPERADA | D68: =+D12+D24+D62 -> 1.2077183e+09
C69: PROVISIÓN ACTUAL | D69: =ROUND(I3,-3) -> 1153906000
C70: AJUSTE A LA PROVISION | D70: =ROUND(((D62*100%)+D12)-D69,-2) -> 53812300
C71: PROVISIÓN FINAL | D71: =+D69+D70 -> 1207718300
C81: MES | D81: CRITERIO 1 | E81: CRITERIO 2 | F81: CRITERIO 3 | G81: TOTAL PROVISIÓN MODELO PERDIDA ESPERADA | H81: PROVISIÓN ACTUAL | I81: AJUSTE A LA PROVISION | J81: PROVISIÓN FINAL | K81: RECAUDO | L81: SALDO CONTABLE POR MES | M81: PROVISION VS CARTERA | N81: TOTAL CARTERA | O81: RECOBRADO | P81: CASTIGADO
C82: MARZO 2025 | D82: 61831570 | E82: 0 | F82: 1.0963578e+09 | G82: 1.1581894e+09 | H82: 1185998000 | I82: -27808600 | J82: 1158189400 | K82: 226734437 | L82: 1437679025 | M82: 0.80559665 | N82: 10078131179 | O82: 8022491492 | P82: 410506751
C83: ABRIL 2025 | D83: 86838136 | E83: 0 | F83: 1.1064173e+09 | G83: 1.1932555e+09 | H83: 1158189000 | I83: 35066500 | J83: 1193255500 | K83: 172548411 | L83: 1525494146 | M83: 0.78220916 | N83: 10338494711 | O83: 8163181055 | P83: 410506751
C84: MAYO 2025 | D84: 84014618 | E84: 0 | F84: 1.0936907e+09 | G84: 1.1777053e+09 | H84: 1193256000 | I84: -15550700 | J84: 1177705300 | K84: 281386638 | L84: 1499516292 | M84: 0.78539013 | N84: 10591333695 | O84: 8432784844 | P84: 410506751
C85: JUNIO 2025 | D85: 85571038 | E85: 0 | F85: 1.0970081e+09 | G85: 1.1825791e+09 | H85: 1177705000 | I85: 4874100 | J85: 1182579100 | K85: 219874012 | L85: 1467717280 | M85: 0.80572677 | N85: 10850646013 | O85: 8686694811 | P85: 481744069
C86: JULIO 2025 | D86: 77071845 | E86: 0 | F86: 1.0420247e+09 | G86: 1.1190965e+09 | H86: 1182579000 | I86: -63482500 | J86: 1119096500 | K86: 297209276 | L86: 1400699685 | M86: 0.79895534 | N86: 11076339938 | O86: 8981020937 | P86: 481744069
C87: AGOSTO 2025 | D87: 85527231 | E87: 0 | F87: 1.068379e+09 | G87: 1.1539062e+09 | H87: 1119097000 | I87: 34809200 | J87: 1153906200 | K87: 160786555 | L87: 1450984915 | M87: 0.7952572 | N87: 11291213433 | O87: 9106858590 | P87: 481744069
C88: SEPTIEMBRE 2025 | D88: =+D65 -> 1.3726199e+08 | E88: 0 | F88: =+D67 -> 1.0704563e+09 | G88: =SUM(D88:F88) -> 1.2077183e+09 | H88: =+D69 -> 1153906000 | I88: =+D70 -> 53812300 | J88: =+D71 -> 1207718300 | K88: =+GETPIVOTDATA("Valor",$C$193,"Fecha de documento",9,"Años",2025) -> 295802141 | L88: =+PROVISION!J23 -> 1412815123 | M88: =IFERROR(J88/L88,0) -> 0.8548311 | N88: ='Resumen General x Edades'!D72 -> 11548845782 | O88: =+PROVISION!C14 -> 9600731677 | P88: ='Resumen General x Edades'!F72 -> 481744069
C89: OCTUBRE 2025 | D89: =+D65 -> 1.3726199e+08 | F89: =+D67 -> 1.0704563e+09 | G89: =SUM(D89:F89) -> 1.2077183e+09 | H89: =+D70 -> 53812300 | I89: =+D70 -> 53812300 | J89: =+D71 -> 1207718300 | K89: =+GETPIVOTDATA("Valor",$C$193,"Fecha de documento",7,"Años",2025) -> 297209276 | L89: =+PROVISION!J23 -> 1412815123 | M89: =IFERROR(J89/L89,0) -> 0.8548311 | N89: ='Resumen General x Edades'!D72 -> 11548845782 | O89: =+PROVISION!C14 -> 9600731677 | P89: ='Resumen General x Edades'!F72 -> 481744069
C90: NOVIEMBRE 2025 | D90: =+D65 -> 1.3726199e+08 | F90: =+D67 -> 1.0704563e+09 | G90: =SUM(D90:F90) -> 1.2077183e+09 | H90: =+D70 -> 53812300 | I90: =+D70 -> 53812300 | J90: =+D71 -> 1207718300 | K90: =+GETPIVOTDATA("Valor",$C$193,"Fecha de documento",7,"Años",2025) -> 297209276 | L90: =+PROVISION!J23 -> 1412815123 | M90: =IFERROR(J90/L90,0) -> 0.8548311 | N90: ='Resumen General x Edades'!D72 -> 11548845782 | O90: =+PROVISION!C14 -> 9600731677 | P90: ='Resumen General x Edades'!F72 -> 481744069
C91: DICIEMBRE 2025 | D91: =+D65 -> 1.3726199e+08 | F91: =+D67 -> 1.0704563e+09 | G91: =SUM(D91:F91) -> 1.2077183e+09 | H91: =+D70 -> 53812300 | I91: =+D70 -> 53812300 | J91: =+D71 -> 1207718300 | K91: =+GETPIVOTDATA("Valor",$C$193,"Fecha de documento",7,"Años",2025) -> 297209276 | L91: =+PROVISION!J23 -> 1412815123 | M91: =IFERROR(J91/L91,0) -> 0.8548311 | N91: ='Resumen General x Edades'!D72 -> 11548845782 | O91: =+PROVISION!C14 -> 9600731677 | P91: ='Resumen General x Edades'!F72 -> 481744069
C96: MODELO
C98: MES | D98: CRITERIO 1 | E98: CRITERIO 2 | F98: CRITERIO 3 | G98: TOTAL PROVISIÓN MODELO PERDIDA ESPERADA | H98: PROVISIÓN ACTUAL | I98: AJUSTE A LA PROVISION | J98: PROVISIÓN FINAL
C99: MARZO 2025 | D99: 61831570 | E99: 0 | F99: 1.0963578e+09 | G99: 1.1581894e+09 | H99: 1185998000 | I99: -27808600 | J99: 1158189400
C100: ABRIL 2025 | D100: 86838136 | E100: 0 | F100: 1.1064173e+09 | G100: 1.1932555e+09 | H100: 1158189000 | I100: 35066500 | J100: 1193255500
C101: MAYO 2025 | D101: 84014618 | E101: 0 | F101: 1.0936907e+09 | G101: 1.1777053e+09 | H101: 1193256000 | I101: -15550700 | J101: 1177705300
C102: JUNIO 2025 | D102: 85571038 | E102: 0 | F102: 1.0970081e+09 | G102: 1.1825791e+09 | H102: 1177705000 | I102: 4874100 | J102: 1182579100
C103: JULIO 2025 | D103: 77071845 | E103: 0 | F103: 1.0420247e+09 | G103: 1.1190965e+09 | H103: 1182579000 | I103: -63482500 | J103: 1119096500
C104: AGOSTO 2025 | D104: 85527231 | E104: 0 | F104: 1.068379e+09 | G104: 1.1539062e+09 | H104: 1119097000 | I104: 34809200 | J104: 1153906200
C105: SEPTIEMBRE 2025 | D105: 1.3726199e+08 | E105: 0 | F105: 1.0919764e+09 | G105: 1.2292384e+09 | H105: 75332400 | I105: 75332400 | J105: 1229238400
C117: RECAUDO
C118: RECAUDO | D118: (Todas)
C120: MES | D120: Suma de RECAUDO
C121: MARZO 2025 | D121: 226734437
C122: ABRIL 2025 | D122: 172548411
C123: MAYO 2025 | D123: 281386638
C124: JUNIO 2025 | D124: 219874012
C125: JULIO 2025 | D125: 297209276
C126: AGOSTO 2025 | D126: 160786555
C127: SEPTIEMBRE 2025 | D127: 297209276
C149: =+C152+D152+E152 -> 10636156160
B151: MES | C151: V Recuperados. | D151: En recuperacion. | E151: Castigado. | F151: saldo catera
B152: ='PRESENT 2'!$O$4 -> JUNIO 2025 | C152: =VLOOKUP(B152,C81:Q91,13,0) -> 8686694811 | D152: =VLOOKUP(B152,C82:Q88,10,0) -> 1467717280 | E152: =VLOOKUP(B152,C81:Q88,14,0) -> 481744069 | F152: =VLOOKUP(B152,C81:Q88,12,0) -> 10850646013
C153: =+C152/$C$149 -> 0.81671373 | D153: =+D152/$C$149 -> 0.13799321 | E153: =+E152/$C$149 -> 0.045293061 | F153: =+F152/$F$152 -> 1
C162: SALDO CONTABLE POR MES | D162: (Todas)
C164: MES | D164: Suma de SALDO CONTABLE POR MES
...

Sheet PRESENT 2
O3: MES
O4: JUNIO 2025
D12: =+'Nuevo Modelo2'!F152 -> 10850646013
D15: =+'Nuevo Modelo2'!C152 -> 8686694811
D17: =+'Nuevo Modelo2'!E152 -> 481744069
D21: =+'Nuevo Modelo2'!D152 -> 1467717280
F44: MES | G44: CRITERIO 1 | H44: CRITERIO 2 | I44: CRITERIO 3 | J44: TOTAL PROVISIÓN | K44: PROVISIÓN ACTUAL | L44: AJUSTE MES | M44: PROVISIÓN FINAL
F45: MARZO 2025 | G45: 61831570 | H45: 0 | I45: 1.0963578e+09 | J45: 1.1581894e+09 | K45: 1185998000 | L45: -27808600 | M45: 1158189400
F46: ABRIL 2025 | G46: 86838136 | H46: 0 | I46: 1.1064173e+09 | J46: 1.1932555e+09 | K46: 1158189000 | L46: 35066500 | M46: 1193255500
F47: MAYO 2025 | G47: 84014618 | H47: 0 | I47: 1.0936907e+09 | J47: 1.1777053e+09 | K47: 1193256000 | L47: -15550700 | M47: 1177705300
F48: JUNIO 2025 | G48: 85571038 | H48: 0 | I48: 1.0970081e+09 | J48: 1.1825791e+09 | K48: 1177705000 | L48: 4874100 | M48: 1182579100 | O48: =VLOOKUP(O4,'Nuevo Modelo2'!C81:M88,11,0) -> 0.80572677
F49: JULIO 2025 | G49: 77071845 | H49: 0 | I49: 1.0420247e+09 | J49: 1.1190965e+09 | K49: 1182579000 | L49: -63482500 | M49: 1119096500
F50: AGOSTO 2025 | G50: 85527231 | H50: 0 | I50: 1.068379e+09 | J50: 1.1539062e+09 | K50: 1119097000 | L50: 34809200 | M50: 1153906200
F51: SEPTIEMBRE 2025 | G51: 1.3726199e+08 | H51: 0 | I51: 1.0919764e+09 | J51: 1.2292384e+09 | K51: 75332400 | L51: 75332400 | M51: 1229238400
G59: G | I59: CRITERIO 1 | J59: CRITERIO 2 | K59: CRITERIO 3
I60: RANGOS PARA MODELO ECL
L66: CONCEPTO | M66: VALOR | N66: %
L67: Total cartera EPS Int. | M67: =+'Nuevo Modelo2'!D187 -> 923145942 | N67: =+M67/PROVISION!$J$23 -> 0.65340888
L70: Total Provision EPS Int. | M70: ='Nuevo Modelo2'!E187 -> 8.3083135e+08 | N70: =+M70/M67 -> 0.9

Sheet Hoja1
A1: MES | B1: CARTERA | C1: % | D1: Recaudo | E1: % | F1: CRITERIO 1 | G1: CRITERIO 2 | H1: CRITERIO 3 | I1: TOTAL PROVISIÓN | J1: PROVISIÓN ACTUAL | K1: AJUSTE MES | L1: PROVISIÓN FINAL | M1: %
A2: ENERO | B2: 1408205062 | D2: 205615651 | F2: 3.9255657e+08 | G2: 128415454 | H2: 60473832 | I2: 581446000 | J2: 774813000 | K2: 9942000 | L2: 784755000
A3: FEBRERO | B3: 1378619137 | C3: =(B3-B2)/B3 -> -0.02146055 | D3: 224465967 | E3: =(D3-D2)/D3 -> 0.083978504 | F3: 3.8765172e+08 | G3: 128415454 | H3: 61611475 | I3: 577679000 | J3: 784755000 | K3: -3767000 | L3: 780988000 | M3: =(L3-L2)/L3 -> -0.0048233776
A4: MARZO | B4: 1287184695 | C4: =(B4-B3)/B4 -> -0.071034438 | D4: 122330374 | E4: =(D4-D3)/D4 -> -0.83491605 | F4: 3.7490315e+08 | G4: 68278528 | H4: 40060324 | I4: 483242000 | J4: 618385000 | K4: 68166000 | L4: 686551000 | M4: =(L4-L3)/L4 -> -0.13755278
A5: ABRIL | B5: 1281480170 | C5: =(B5-B4)/B5 -> -0.0044515125 | D5: 180618914 | E5: =(D5-D4)/D5 -> 0.32271559 | F5: 42379011 | G5: 0 | H5: 1.0818676e+09 | I5: 1.1242466e+09 | J5: 686551000 | K5: 69889000 | L5: 756440000 | M5: =(L5-L4)/L5 -> 0.092391994
A6: MAYO | B6: 1337100352 | C6: =(B6-B5)/B6 -> 0.041597612 | D6: 155720180 | E6: =(D6-D5)/D6 -> -0.15989407 | F6: 53210372 | G6: 0 | H6: 1.0711907e+09 | I6: 1.1244011e+09 | J6: 756440000 | K6: 68055000 | L6: 824495000 | M6: =(L6-L5)/L6 -> 0.082541434
A7: JUNIO | B7: 1231303460 | C7: =(B7-B6)/B7 -> -0.085922679 | D7: 183387574 | E7: =(D7-D6)/D7 -> 0.15086842 | F7: 55803331 | G7: 0 | H7: 9.684463e+08 | I7: 1.0242496e+09 | J7: 684946000 | K7: 126271000 | L7: 811217000 | M7: =(L7-L6)/L7 -> -0.016368
A8: JULIO | B8: 1315298308 | C8: =(B8-B7)/B8 -> 0.063859922 | D8: 123694311 | E8: =(D8-D7)/D8 -> -0.48258697 | F8: 46317725 | G8: 0 | H8: 1081342179 | I8: 1.1276599e+09 | J8: 811217000 | K8: 143456000 | L8: 954673200 | M8: =(L8-L7)/L8 -> 0.15026734
A9: AGOSTO | B9: 1400394588 | C9: =(B9-B8)/B9 -> 0.06076593 | D9: 165055182 | E9: =(D9-D8)/D9 -> 0.25058814 | F9: 56047794 | G9: 0 | H9: 1.1536638e+09 | I9: 1.2097116e+09 | J9: 954673000 | K9: 139702100 | L9: 1094375100 | M9: =(L9-L8)/L9 -> 0.12765449
A10: SEPTIEMBRE | B10: 1441637977 | C10: =(B10-B9)/B10 -> 0.0286087 | D10: 150154070 | E10: =(D10-D9)/D10 -> -0.099238815 | F10: 48127277 | G10: 0 | H10: 1.2330227e+09 | I10: 1224259300 | J10: 1094375000 | K10: 186775000 | L10: 1281150000 | M10: =(L10-L9)/L10 -> 0.14578691

Sheet X Año
B2: SALDO CARTERA POR AÑOS
B7: Año | C7: Total Incapacidades | D7: Valores Recuperados | F7: No cobrables en resultados - CASTIGO | H7: Saldo por Año
B8: Total 2018 | C8: 1915461888 | D8: =+E8/C8 -> 0.92594113 | E8: 1773604941 | F8: =+G8/C8 -> 0.074058872 | G8: 141856947 | H8: =+I8/C8 -> 0 | I8: =+C8-E8-G8 -> 0
B9: Total 2019 | C9: 2265339149 | D9: =+E9/C9 -> 0.9132175 | E9: 2068747351 | F9: =+G9/C9 -> 0.086782501 | G9: 1.965918e+08 | H9: =+I9/C9 -> 1.1222635e-10 | I9: =+C9-E9-G9 -> 0.25423074
B10: Total 2020 | C10: 2149518413 | D10: =+E10/C10 -> 0.8093464 | E10: 1739704993 | F10: =+G10/C10 -> 0.1906536 | G10: 409813420 | H10: =+I10/C10 -> 0 | I10: =+C10-E10-G10 -> 0
B11: Total 2021 | C11: =+VLOOKUP(B11,'Resumen General x Edades'!A:D,4,0) -> 2147464322 | D11: =+E11/C11 -> 0.86166027 | E11: =VLOOKUP(B11,'Resumen General x Edades'!A:E,5,0) -> 1850384688 | F11: =+G11/C11 -> 0.13833973 | G11: =+VLOOKUP(B11,'Resumen General x Edades'!A:F,6,0) -> 297079634 | H11: =+I11/C11 -> 0 | I11: =+C11-E11-G11 -> 0
B12: Total 2022 | C12: =+VLOOKUP(B12,'Resumen General x Edades'!A:D,4,0) -> 2181232827 | D12: =+E12/C12 -> 0.84868278 | E12: =VLOOKUP(B12,'Resumen General x Edades'!A:E,5,0) -> 1851174732 | F12: =+G12/C12 -> 0.084660579 | G12: =+VLOOKUP(B12,'Resumen General x Edades'!A:F,6,0) -> 184664435 | H12: =+I12/C12 -> 0.066656644 | I12: =+C12-E12-G12 -> 145393660
B13: Total 2023 | C13: =+VLOOKUP(B13,'Resumen General x Edades'!A:D,4,0) -> 2457236468 | D13: =+E13/C13 -> 0.86334803 | E13: =VLOOKUP(B13,'Resumen General x Edades'!A:E,5,0) -> 2121450256 | F13: =+G13/C13 -> 0 | G13: =+VLOOKUP(B13,'Resumen General x Edades'!A:F,6,0) -> 0 | H13: =+I13/C13 -> 0.13665197 | I13: =+C13-E13-G13 -> 335786212
B14: Total 2024 | C14: =+VLOOKUP(B14,'Resumen General x Edades'!A:D,4,0) -> 2492212944 | D14: =+E14/C14 -> 0.79391417 | E14: =VLOOKUP(B14,'Resumen General x Edades'!A:E,5,0) -> 1978603166 | F14: =+G14/C14 -> 0 | G14: =+VLOOKUP(B14,'Resumen General x Edades'!A:F,6,0) -> 0 | H14: =+I14/C14 -> 0.20608583 | I14: =+C14-E14-G14 -> 513609778
B15: Total 2025 | C15: =+VLOOKUP(B15,'Resumen General x Edades'!A:D,4,0) -> 2270699221 | D15: =+E15/C15 -> 0.79231931 | E15: =VLOOKUP(B15,'Resumen General x Edades'!A:E,5,0) -> 1799118835 | F15: =+G15/C15 -> 0 | G15: =+VLOOKUP(B15,'Resumen General x Edades'!A:F,6,0) -> 0 | H15: =+I15/C15 -> 0.20768069 | I15: =+C15-E15-G15 -> 471580386
B16: Totales | C16: =SUM(C8:C15) -> 17879165232 | D16: =+E16/C16 -> 0.84918892 | E16: =SUM(E8:E15) -> 15182788962 | F16: =+G16/C16 -> 0.068795507 | G16: =SUM(G8:G15) -> 1.2300062e+09 | H16: =+I16/C16 -> 0.082015576 | I16: =SUM(I8:I15) -> 1.46637e+09

Sheet X EPS
B2: SALDO CARTERA POR EPS
B7: NOMBRE | C7: 0-180 | D7: 181-209 | E7: 210-239 | F7: 240-269 | G7: 270-299 | H7: 300 en adelante | I7: TOTAL
B8: A.I.C. | H8: 23015 | I8: =+SUM(C8:H8) -> 23015
B9: ALIANSALUD EPS (ANTES COLMEDICA) | C9: 8952704 | D9: 2326559 | H9: 69174650 | I9: =+SUM(C9:H9) -> 80453913
B10: AMBUQ | H10: 0 | I10: =+SUM(C10:H10) -> 0
B11: ASMET SALUD EPS SAS | E11: 97657 | G11: 135661 | H11: 1378542 | I11: =+SUM(C11:H11) -> 1611860
B12: CAJACOPI | C12: 125206 | H12: 0 | I12: =+SUM(C12:H12) -> 125206
B13: CAJACOPI ATLANTICO | H13: 8174496 | I13: =+SUM(C13:H13) -> 8174496
B14: CAPITAL SALUD | C14: 44104 | G14: 20139 | H14: 1433852 | I14: =+SUM(C14:H14) -> 1498095
B15: CAPRESOCA | C15: 881123 | D15: 88208 | E15: 220707 | G15: 601388 | H15: 8417446 | I15: =+SUM(C15:H15) -> 10208872
B16: COLPATRIA ARP | H16: 14001291 | I16: =+SUM(C16:H16) -> 14001291
B17: COMFAMILIAR GUAJIRA | H17: 418269 | I17: =+SUM(C17:H17) -> 418269
B18: COMFAMILIAR HUILA | H18: 42223 | I18: =+SUM(C18:H18) -> 42223
B19: COMFAORIENTE | H19: 624894 | I19: =+SUM(C19:H19) -> 624894
B20: COMFENALCO VALLE | C20: 1069432 | D20: 120683 | E20: 771643 | F20: 25152 | H20: 35892792 | I20: =+SUM(C20:H20) -> 37879702
B21: COMPARTA | H21: 249118 | I21: =+SUM(C21:H21) -> 249118
B22: COMPENSAR | C22: 18957385 | D22: 2763588 | E22: 2133569 | F22: 6473375 | G22: 6038056 | H22: 78092582 | I22: =+SUM(C22:H22) -> 114458555
B23: CONVIDA | H23: 15491 | I23: =+SUM(C23:H23) -> 15491
B24: COOMEVA | H24: 20780668 | I24: =+SUM(C24:H24) -> 20780668
B25: COOSALUD EPS | C25: 2734457 | D25: 59858 | G25: 116785 | H25: 12395261 | I25: =+SUM(C25:H25) -> 15306361
B26: COOSALUD MOVILIDAD | C26: 557514 | D26: 44104 | H26: 1330780 | I26: =+SUM(C26:H26) -> 1932398
B27: DUSAKAWI | H27: 46474 | I27: =+SUM(C27:H27) -> 46474
B28: EMPRESAS PUBLICAS DE MEDELLIN DEPARTAMENTO MEDICO | C28: 47016 | E28: 66226 | G28: 32529 | H28: 97834 | I28: =+SUM(C28:H28) -> 243605
B29: EMSSANAR | C29: 107899 | G29: 80697 | H29: 9382253 | I29: =+SUM(C29:H29) -> 9570849
B30: EPS ECOOPSOS S.A.S | H30: 59131 | I30: =+SUM(C30:H30) -> 59131
B31: EPS MUTUAL SER | C31: 496375 | D31: 25228 | F31: 889736 | G31: 1234264 | H31: 3854419 | I31: =+SUM(C31:H31) -> 6500022
B32: EPS SURA (ANTES SUSALUD) | C32: 28908322 | D32: 2934238 | E32: 2294383 | F32: 8291910 | G32: 5606325 | H32: 178687546 | I32: =+SUM(C32:H32) -> 226722724
B33: FAMISANAR | C33: 27198482 | D33: 1612236 | E33: 3636498 | F33: 1685259 | G33: 475727 | H33: 156547887 | I33: =+SUM(C33:H33) -> 191156089
B34: FOSYGA | C34: 2491396 | F34: 1852374 | H34: 10914242 | I34: =+SUM(C34:H34) -> 15258012
B35: MEDIMAS EPS | H35: 22842256 | I35: =+SUM(C35:H35) -> 22842256
B36: MUTUAL SER | C36: 306109 | D36: 286979 | E36: 57369 | G36: 338684 | H36: 8142548 | I36: =+SUM(C36:H36) -> 9131689
B37: NUEVA E.P.S. | C37: 32051497 | D37: 4152336 | E37: 4750824 | F37: 3557549 | G37: 4368596 | H37: 145845612 | I37: =+SUM(C37:H37) -> 194726414
B38: NUEVA EPS MOVILIDAD | C38: 1233838 | F38: 22052 | H38: 2585570 | I38: =+SUM(C38:H38) -> 3841460
B39: S.O.S. SERVICIO OCCIDENTAL DE SALUD S.A. | C39: 401419 | D39: 155682 | E39: 695725 | F39: 1059037 | G39: 27051 | H39: 35770906 | I39: =+SUM(C39:H39) -> 38109820
B40: SALUD MIA EPS | C40: 548884 | H40: 2378990 | I40: =+SUM(C40:H40) -> 2927874
B41: SALUD TOTAL | C41: 55876514 | D41: 4089575 | E41: 18778554 | F41: 12976769 | G41: 5244108 | H41: 167336678 | I41: =+SUM(C41:H41) -> 264302198
B42: SANITAS | C42: 59779996 | D42: 14900755 | E42: 6279403 | F42: 19801311 | G42: 10665590 | H42: 296090639 | I42: =+SUM(C42:H42) -> 407517694
B43: SAVIA SALUD | H43: 887185 | I43: =+SUM(C43:H43) -> 887185
B44: SAVIA SALUD | C44: 983558 | F44: 176416 | H44: 45021 | I44: =+SUM(C44:H44) -> 1204995
B45: TOTAL | C45: =SUM(C8:C44) -> 243753230 | D45: =SUM(D8:D44) -> 33560029 | E45: =SUM(E8:E44) -> 39782558 | F45: =SUM(F8:F44) -> 56810940 | G45: =SUM(G8:G44) -> 34985600 | H45: =SUM(H8:H44) -> 1293960561 | I45: =SUM(I8:I44) -> 1702852918

Sheet Nuevo Modelo2 (2)
A2: MODELO INICIAL (3 CRITERIOS)
A3: 1. MODELO DE PROVISIÓN SALDO GENERAL | H3: Prov. Actual | I3: =+PROVISION!R9 -> 1153905731
A4: MODELO ECL 2024 | H4: Pérdida con Modelo | I4: Disminicion Prov mes a mes
A5: Total Cartera | B5: =SUM(B6:B11) -> 179783051
A6: 0-180 | B6: 13884054 | C6: 0.36344208 | D6: =+B6*C6 -> 5046049.4 | G6: Enero | H6: =+D12 -> 57831458 | I6: =+$I$3-H6 -> 1.0960743e+09
A7: 181-209 | B7: 19305538 | C7: 0.36344208 | D7: =+B7*C7 -> 7016444.9 | G7: Febrero
A8: 210-239 | B8: 39011829 | C8: 0.36344208 | D8: =+B8*C8 -> 14178540 | G8: Marzo
A9: 240-269 | B9: 45597058 | C9: 0.36344208 | D9: =+B9*C9 -> 16571890 | G9: Abril
A10: 270-299 | B10: 56717772 | C10: 0.24229472 | D10: =+B10*C10 -> 13742417 | G10: Mayo
A11: 300 en adelante | B11: 5266800 | C11: 0.24229472 | D11: =+B11*C11 -> 1276117.8 | G11: Junio
A12: Total Provision | D12: =SUM(D6:D11) -> 57831458 | G12: Julio
G13: Agosto
A14: 2. CARTERA MÁS DE UN AÑO Y MÁS DE 80 MILLONES -(Cartera por cobrar de más de 1 año desglosado por eps y por saldos mayores a 80 millones. (Sobre ese saldo mirar el % castigado y aplicar a la historia de pérdida) | G14: Septiembre
G15: Octubre
G16: Noviembre
A17: EPS | B17: Cartera más de un año | C17: % castigado | D17: Valor provisión | G17: Diciembre
H19: RANGOS PARA MODELO ECL
H20: 0-180 | I20: En plazo
H21: 181-209 | I21: 0-30
H22: 210-239 | I22: 31-60
H23: 240-269 | I23: 61-90
A24: Total general | B24: =+SUM(B19:B23) -> 0 | D24: =+SUM(D19:D23) -> 0 | H24: 270-299 | I24: 91-180
H25: 300 en adelante | I25: Más de 180
A26: 3 criterio. Cartera por cobrar de más de 1 año desglosado por eps y por saldos menores a 80 millones y especial (Aquí van incluidas todas las eps de liquidación e intervención) Se les debe asignar porcentaje de castigo (90-100%) de acuerdo al movimientos de cada una.
A28: EPS | B28: Cartera más de un año | C28: % castigado | D28: Valor provisión | E28: INTERVENIDAS
A29: SANITAS | B29: =F29-IFERROR(VLOOKUP(A29,'Resumen General x Edades'!D:E,2,0),0) -> 334380218 | C29: 0.9 | D29: =+B29*C29 -> 3.009422e+08 | E29: =IFERROR(VLOOKUP(A29,$I$37:$I$49,1,0)," ") -> SANITAS | F29: 335246885
A30: EPS SURA (ANTES SUSALUD) | B30: =F30-IFERROR(VLOOKUP(A30,'Resumen General x Edades'!D:E,2,0),0) -> 201087033 | C30: 0.9 | D30: =+B30*C30 -> 1.8097833e+08 | E30: =IFERROR(VLOOKUP(A30,$I$37:$I$49,1,0)," ") -> EPS SURA (ANTES SUSALUD) | F30: 201087033
A31: SALUD TOTAL | B31: =F31-IFERROR(VLOOKUP(A31,'Resumen General x Edades'!D:E,2,0),0) -> 105723398 | C31: 0.9 | D31: =+B31*C31 -> 95151058 | E31: =IFERROR(VLOOKUP(A31,$I$37:$I$49,1,0)," ") | F31: 105723398
A32: FAMISANAR | B32: =F32-IFERROR(VLOOKUP(A32,'Resumen General x Edades'!D:E,2,0),0) -> 163758425 | C32: 0.9 | D32: =+B32*C32 -> 1.4738258e+08 | E32: =IFERROR(VLOOKUP(A32,$I$37:$I$49,1,0)," ") -> FAMISANAR | F32: 163796244
A33: NUEVA E.P.S. | B33: =F33-IFERROR(VLOOKUP(A33,'Resumen General x Edades'!D:E,2,0),0) -> 169352181 | C33: 0.9 | D33: =+B33*C33 -> 1.5241696e+08 | E33: =IFERROR(VLOOKUP(A33,$I$37:$I$49,1,0)," ") -> NUEVA E.P.S. | F33: 170002181
A34: COMPENSAR | B34: =F34-IFERROR(VLOOKUP(A34,'Resumen General x Edades'!D:E,2,0),0) -> 98554067 | C34: 0.9 | D34: =+B34*C34 -> 88698660 | E34: =IFERROR(VLOOKUP(A34,$I$37:$I$49,1,0)," ") -> COMPENSAR | F34: 107591423
A35: ALIANSALUD EPS (ANTES COLMEDICA) | B35: =F35-IFERROR(VLOOKUP(A35,'Resumen General x Edades'!D:E,2,0),0) -> 38528935 | C35: 0.9 | D35: =+B35*C35 -> 34676042 | E35: =IFERROR(VLOOKUP(A35,$I$37:$I$49,1,0)," ") | F35: 38528935
A36: S.O.S. SERVICIO OCCIDENTAL DE SALUD S.A. | B36: =F36-IFERROR(VLOOKUP(A36,'Resumen General x Edades'!D:E,2,0),0) -> 33212106 | C36: 0.9 | D36: =+B36*C36 -> 29890895 | E36: =IFERROR(VLOOKUP(A36,$I$37:$I$49,1,0)," ") | F36: 33212106
A37: COMFENALCO VALLE | B37: =F37-IFERROR(VLOOKUP(A37,'Resumen General x Edades'!D:E,2,0),0) -> 33252061 | C37: 0.9 | D37: =+B37*C37 -> 29926855 | E37: =IFERROR(VLOOKUP(A37,$I$37:$I$49,1,0)," ") | F37: 33299511 | H37: 8600669427 | I37: COMPENSAR
A38: MEDIMAS EPS | B38: =F38-IFERROR(VLOOKUP(A38,'Resumen General x Edades'!D:E,2,0),0) -> 21984063 | C38: 0.9 | D38: =+B38*C38 -> 19785657 | E38: =IFERROR(VLOOKUP(A38,$I$37:$I$49,1,0)," ") -> MEDIMAS EPS | F38: 21984063 | H38: 8140003371 | I38: EMSSANAR
A39: COOMEVA | B39: =F39-IFERROR(VLOOKUP(A39,'Resumen General x Edades'!D:E,2,0),0) -> 19999911 | C39: 0.9 | D39: =+B39*C39 -> 17999920 | E39: =IFERROR(VLOOKUP(A39,$I$37:$I$49,1,0)," ") -> COOMEVA | F39: 19999911 | H39: 8000887022 | I39: EPS SURA (ANTES SUSALUD)
A40: COLPATRIA ARP | B40: =F40-IFERROR(VLOOKUP(A40,'Resumen General x Edades'!D:E,2,0),0) -> 173030 | C40: 0.9 | D40: =+B40*C40 -> 155727 | E40: =IFERROR(VLOOKUP(A40,$I$37:$I$49,1,0)," ") | F40: 13475253 | H40: 8300035647 | I40: FAMISANAR
A41: FOSYGA | B41: =F41-IFERROR(VLOOKUP(A41,'Resumen General x Edades'!D:E,2,0),0) -> 8238973 | C41: 0.9 | D41: =+B41*C41 -> 7415075.7 | E41: =IFERROR(VLOOKUP(A41,$I$37:$I$49,1,0)," ") | F41: 8238973 | H41: 8002514406 | I41: SANITAS
A42: COOSALUD EPS | B42: =F42-IFERROR(VLOOKUP(A42,'Resumen General x Edades'!D:E,2,0),0) -> 10880279 | C42: 0.9 | D42: =+B42*C42 -> 9792251.1 | E42: =IFERROR(VLOOKUP(A42,$I$37:$I$49,1,0)," ") | F42: 11460279 | H42: 9001562642 | I42: NUEVA E.P.S.
A43: EMSSANAR | B43: =F43-IFERROR(VLOOKUP(A43,'Resumen General x Edades'!D:E,2,0),0) -> 9533222 | C43: 0.9 | D43: =+B43*C43 -> 8579899.8 | E43: =IFERROR(VLOOKUP(A43,$I$37:$I$49,1,0)," ") -> EMSSANAR | F43: 9533222 | I43: MEDIMAS EPS
A44: CAJACOPI ATLANTICO | B44: =F44-IFERROR(VLOOKUP(A44,'Resumen General x Edades'!D:E,2,0),0) -> 7867375 | C44: 0.9 | D44: =+B44*C44 -> 7080637.5 | E44: =IFERROR(VLOOKUP(A44,$I$37:$I$49,1,0)," ") | F44: 7867375 | I44: COOMEVA
A45: MUTUAL SER | B45: =F45-IFERROR(VLOOKUP(A45,'Resumen General x Edades'!D:E,2,0),0) -> 7469083 | C45: 0.9 | D45: =+B45*C45 -> 6722174.7 | E45: =IFERROR(VLOOKUP(A45,$I$37:$I$49,1,0)," ") | F45: 7469083
A46: CAPRESOCA | B46: =F46-IFERROR(VLOOKUP(A46,'Resumen General x Edades'!D:E,2,0),0) -> -2686435 | C46: 0.9 | D46: =+B46*C46 -> -2417791.5 | E46: =IFERROR(VLOOKUP(A46,$I$37:$I$49,1,0)," ") | F46: 2773565
A47: SALUD MIA EPS | B47: =F47-IFERROR(VLOOKUP(A47,'Resumen General x Edades'!D:E,2,0),0) -> 1342050 | C47: 0.9 | D47: =+B47*C47 -> 1207845 | E47: =IFERROR(VLOOKUP(A47,$I$37:$I$49,1,0)," ") | F47: 1342050
A48: CAPITAL SALUD | B48: =F48-IFERROR(VLOOKUP(A48,'Resumen General x Edades'!D:E,2,0),0) -> 888699 | C48: 0.9 | D48: =+B48*C48 -> 799829.1 | E48: =IFERROR(VLOOKUP(A48,$I$37:$I$49,1,0)," ") | F48: 888699
A49: SAVIA SALUD | B49: =F49-IFERROR(VLOOKUP(A49,'Resumen General x Edades'!D:E,2,0),0) -> 853853 | C49: 0.9 | D49: =+B49*C49 -> 768467.7 | E49: =IFERROR(VLOOKUP(A49,$I$37:$I$49,1,0)," ") | F49: 853853
A50: COMFAORIENTE | B50: =F50-IFERROR(VLOOKUP(A50,'Resumen General x Edades'!D:E,2,0),0) -> 554813 | C50: 0.9 | D50: =+B50*C50 -> 499331.7 | E50: =IFERROR(VLOOKUP(A50,$I$37:$I$49,1,0)," ") | F50: 554813
A51: ASMET SALUD EPS SAS | B51: =F51-IFERROR(VLOOKUP(A51,'Resumen General x Edades'!D:E,2,0),0) -> 1457312 | C51: 0.9 | D51: =+B51*C51 -> 1311580.8 | E51: =IFERROR(VLOOKUP(A51,$I$37:$I$49,1,0)," ") | F51: 1457312
A52: COMFAMILIAR GUAJIRA | B52: =F52-IFERROR(VLOOKUP(A52,'Resumen General x Edades'!D:E,2,0),0) -> 402554 | C52: 0.9 | D52: =+B52*C52 -> 362298.6 | E52: =IFERROR(VLOOKUP(A52,$I$37:$I$49,1,0)," ") | F52: 402554
A53: COMPARTA | B53: =F53-IFERROR(VLOOKUP(A53,'Resumen General x Edades'!D:E,2,0),0) -> 239758 | C53: 0.9 | D53: =+B53*C53 -> 215782.2 | E53: =IFERROR(VLOOKUP(A53,$I$37:$I$49,1,0)," ") | F53: 239758
A54: EMPRESAS PUBLICAS DE MEDELLIN DEPARTAMENTO MEDICO | B54: =F54-IFERROR(VLOOKUP(A54,'Resumen General x Edades'!D:E,2,0),0) -> -7589 | C54: 0.9 | D54: =+B54*C54 -> -6830.1 | E54: =IFERROR(VLOOKUP(A54,$I$37:$I$49,1,0)," ") | F54: 33649
A55: EPS ECOOPSOS S.A.S | B55: =F55-IFERROR(VLOOKUP(A55,'Resumen General x Edades'!D:E,2,0),0) -> 56911 | C55: 0.9 | D55: =+B55*C55 -> 51219.9 | E55: =IFERROR(VLOOKUP(A55,$I$37:$I$49,1,0)," ") | F55: 56911
A56: DUSAKAWI | B56: =F56-IFERROR(VLOOKUP(A56,'Resumen General x Edades'!D:E,2,0),0) -> 44728 | C56: 0.9 | D56: =+B56*C56 -> 40255.2 | E56: =IFERROR(VLOOKUP(A56,$I$37:$I$49,1,0)," ") | F56: 44728
... A59: CONVIDA | B59: =F59-IFERROR(VLOOKUP(A59,'Resumen General x Edades'!D:E,2,0),0) -> 14909 | C59: 0.9 | D59: =+B59*C59 -> 13418.1 | E59: =IFERROR(VLOOKUP(A59,$I$37:$I$49,1,0)," ") | F59: 14909
A60: EPS MUTUAL SER | B60: =F60-IFERROR(VLOOKUP(A60,'Resumen General x Edades'!D:E,2,0),0) -> 285355 | C60: 0.9 | D60: =+B60*C60 -> 256819.5 | F60: 285355
A61: TOTAL GENERAL | B61: =+SUM(B29:B60) -> 1267504066 | C61: 0.9 | D61: =+SUM(D29:D60) -> 1.1407537e+09 | F61: =SUM(F29:F60) -> 1297526819
C64: CRITERIO 1 | D64: =+D12 -> 57831458
C65: CRITERIO 2 | D65: =+D24 -> 0
C66: CRITERIO 3 | D66: =+D61 -> 1.1407537e+09
C67: TOTAL PROVISIÓN MODELO PERDIDA ESPERADA | D67: =+D12+D24+D61 -> 1.1985851e+09
C68: PROVISIÓN ACTUAL | D68: =ROUND(I3,-3) -> 1153906000
C69: AJUSTE A LA PROVISION | D69: =ROUND(((D61*L71)+D12)-D68,-2) -> 44679100
C70: PROVISIÓN FINAL | D70: =+D68+D69 -> 1198585100
F71: 0.59542591 | G71: 0.66002591 | H71: 0.72002591 | I71: 0.78002591 | J71: 0.84002591 | K71: 0.90002591 | L71: 1
C72: OBSERVACIONES: 100% primer Criterio + 90% Tercer Criterio | F72: 4 | G72: 5 | H72: 6 | I72: 7 | J72: 8 | K72: 9 | L72: 10
C80: MES | D80: CRITERIO 1 | E80: CRITERIO 2 | F80: CRITERIO 3 | G80: TOTAL PROVISIÓN MODELO PERDIDA ESPERADA | H80: PROVISIÓN ACTUAL | I80: AJUSTE A LA PROVISION | J80: PROVISIÓN FINAL | K80: RECAUDO | L80: SALDO CONTABLE POR MES | M80: PROVISION VS CARTERA | N80: TOTAL CARTERA | O80: RECOBRADO | P80: CASTIGADO
C81: FEBRERO 2024 | D81: 3.8765172e+08 | E81: 128415454 | F81: 61611475 | G81: 577679000 | H81: 784755000 | I81: -3767000 | J81: 780988000 | K81: =+'X Pago'!D14 -> 224465967 | L81: 1378619137 | M81: =J81/L81 -> 0.56650019 | N81: 9323138631 | O81: 7607633507 | P81: 336885987
C82: MARZO 224 | D82: 3.7490315e+08 | E82: 68278528 | F82: 40060324 | G82: 483242000 | H82: 618385000 | I82: 68166000 | J82: 686551000 | K82: =+'X Pago'!E14 -> 122330374 | L82: 1287184695 | M82: =J82/L82 -> 0.53337412 | N82: 9503144347 | O82: 7719853190 | P82: 496106462
C83: ABRIL 2024 | D83: 42379011 | E83: 0 | F83: 1.0818676e+09 | G83: 1.1242466e+09 | H83: 686551000 | I83: 69889000 | J83: 756440000 | K83: =+'X Pago'!F14 -> 180618914 | L83: 1281480170 | M83: =J83/L83 -> 0.59028615 | N83: 7527711538 | O83: 6159938326 | P83: 86293042
C84: MAYO 2024 | D84: 53210372 | E84: 0 | F84: 1.0711907e+09 | G84: 1.1244011e+09 | H84: 756440000 | I84: 68055000 | J84: 824495000 | K84: =+'X Pago'!G14 -> 155720180 | L84: 1337100352 | M84: =J84/L84 -> 0.61662911 | N84: 7739051900 | O84: 6315658506 | P84: 86293042
C85: JUNIO2024 | D85: 55803331 | E85: 0 | F85: 9.684463e+08 | G85: 1.0242496e+09 | H85: 684946000 | I85: 126271000 | J85: 811217000 | K85: =+'X Pago'!H14 -> 183387574 | L85: 1231303460 | M85: =J85/L85 -> 0.65882784 | N85: 7956289406 | O85: 6499143630 | P85: 225842316
C86: JULIO 2024 | D86: 46317725 | E86: 0 | F86: 1081342179 | G86: 1.1276599e+09 | H86: 811217000 | I86: 143456000 | J86: 954673200 | K86: =+'X Pago'!I14 -> 123694311 | L86: 1315298308 | M86: =J86/L86 -> 0.72582257 | N86: 8160639421 | O86: 6619498797 | P86: 225842316
C87: AGOSTO 2024 | D87: 56047794 | E87: 0 | F87: 1.1536638e+09 | G87: 1.2097116e+09 | H87: 954673000 | I87: 139702100 | J87: 1094375100 | K87: 165055182 | L87: 1400394588 | M87: 0.78147624 | N87: 8416771038 | O87: 6790534134 | P87: 225842316
C88: SEPTIEMBRE 2024 | D88: 48127277 | E88: 0 | F88: 1.2330227e+09 | G88: 1224259300 | H88: 1094375000 | I88: 186775000 | J88: 1281150000 | K88: 150154070 | L88: 1441637977 | M88: 0.88867664 | N88: 8606044460 | O88: 6938806439 | P88: 225842316
C89: OCTUBRE 2024 | D89: 57486941 | E89: 0 | F89: 1.2916157e+09 | G89: 1.3491027e+09 | H89: 1281150000 | I89: 67952700 | J89: 1349102700 | K89: 157068778 | L89: 1494454722 | M89: 0.90273909 | N89: 8812397375 | O89: 6972093276 | P89: 225842316
C90: NOVIEMBRE 2024 | D90: 54645989 | E90: 0 | F90: 1.3037512e+09 | G90: 1.3583972e+09 | H90: 1349103000 | I90: 9294200 | J90: 1358397200 | K90: 189628881 | L90: 1532827560 | M90: =IFERROR(J90/L90,0) -> 0.88620353 | N90: 9053519653 | O90: 7197670142 | P90: 225842316
C91: DICIEMBRE 2024 | D91: 65408099 | E91: 0 | F91: 1.0932862e+09 | G91: 1.1586943e+09 | H91: 1155145000 | I91: 3549300 | J91: 1158694300 | K91: 172746295 | L91: 1396470738 | M91: 0.82973045 | N91: 9278146561 | O91: 7350054259 | P91: 410506751
C92: ENERO 2025 | D92: =+D64 -> 57831458 | E92: 0 | F92: =+D66 -> 1.1407537e+09 | G92: =SUM(D92:F92) -> 1.1985851e+09 | H92: =+D68 -> 1153906000 | I92: =+D69 -> 44679100 | J92: =+D70 -> 1198585100 | K92: =+E199 -> 293135847 | L92: =+PROVISION!J23 -> 1412815123 | M92: =IFERROR(J92/L92,0) -> 0.84836656 | N92: ='Resumen General x Edades'!D72 -> 11548845782 | O92: =+PROVISION!C14 -> 9600731677 | P92: ='Resumen General x Edades'!F72 -> 481744069
C100: MODELO
C102: MES | D102: CRITERIO 1 | E102: CRITERIO 2 | F102: CRITERIO 3 | G102: TOTAL PROVISIÓN MODELO PERDIDA ESPERADA | H102: PROVISIÓN ACTUAL | I102: AJUSTE A LA PROVISION | J102: PROVISIÓN FINAL
C103: ENERO 2025 | D103: 57831458 | E103: 0 | F103: 1.0490795e+09 | G103: 1.1069109e+09 | H103: 1158694000 | I103: -51783100 | J103: 1106910900
C121: RECAUDO
C122: RECAUDO | D122: 293135847
C124: MES | D124: Suma de RECAUDO
C125: ENERO 2025 | D125: 293135847
B155: MES | C155: V Recuperados. | D155: En recuperacion. | E155: Castigado. | F155: saldo catera
B156: ='PRESENT 2'!$O$4 -> JUNIO 2025 | C156: =VLOOKUP(B156,C81:Q92,13,0) -> #N/A | D156: =VLOOKUP(B156,C80:Q92,10,0) -> #N/A | E156: =VLOOKUP(B156,C80:Q92,14,0) -> #N/A | F156: =VLOOKUP(B156,C80:Q92,12,0) -> #N/A
C166: SALDO CONTABLE POR MES | D166: 1443511348
C168: MES | D168: Suma de SALDO CONTABLE POR MES
C169: ENERO 2025 | D169: 1443511348
C182: EPS | D182: VALOR TOTAL | E182: VALOR PROVISIONADO
C183: SANITAS | D183: =VLOOKUP(C183,$A$28:D61,2,0) -> 334380218 | E183: =VLOOKUP(C183,$A$28:D61,4,0) -> 3.009422e+08
C184: EPS SURA (ANTES SUSALUD) | D184: =VLOOKUP(C184,$A$28:D62,2,0) -> 201087033 | E184: =VLOOKUP(C184,$A$28:D62,4,0) -> 1.8097833e+08
C185: NUEVA E.P.S. | D185: =VLOOKUP(C185,$A$28:D63,2,0) -> 169352181 | E185: =VLOOKUP(C185,$A$28:D63,4,0) -> 1.5241696e+08
C186: FAMISANAR | D186: =VLOOKUP(C186,$A$28:D64,2,0) -> 163758425 | E186: =VLOOKUP(C186,$A$28:D64,4,0) -> 1.4738258e+08
C187: COMPENSAR | D187: =VLOOKUP(C187,$A$28:D65,2,0) -> 98554067 | E187: =VLOOKUP(C187,$A$28:D65,4,0) -> 88698660
C188: MEDIMAS EPS | D188: =VLOOKUP(C188,$A$28:D66,2,0) -> 21984063 | E188: =VLOOKUP(C188,$A$28:D66,4,0) -> 19785657
C189: COOMEVA | D189: =VLOOKUP(C189,$A$28:D67,2,0) -> 19999911 | E189: =VLOOKUP(C189,$A$28:D67,4,0) -> 17999920
C190: EMSSANAR | D190: =VLOOKUP(C190,$A$28:D68,2,0) -> 9533222 | E190: =VLOOKUP(C190,$A$28:D68,4,0) -> 8579899.8
C191: TOTAL | D191: =SUM(D183:D190) -> 1018649120 | E191: =SUM(E183:E190) -> 9.1678421e+08 | F191: =D191/PROVISION!J23 -> 0.72100666
...

Sheet X Pago
B2: RESUMEN RECAUDO MES
B7: Año | C7: 1 | D7: 2 | E7: 3 | F7: 4 | G7: 5 | H7: 6 | I7: 7 | J7: 8 | K7: 9 | L7: 10 | M7: 11 | N7: 12
B8: Total 2020 | C8: 184968 | D8: 483146
B9: Total 2021 | C9: 13990236 | D9: 5927233 | E9: 11637096 | F9: 12755426 | G9: 2732913 | H9: 1780520 | I9: 3773536 | J9: 0 | K9: 242272 | L9: 242272
B10: Total 2022 | C10: 23189049 | D10: 10045515 | E10: 6245706 | F10: 5775314 | G10: 2288827 | H10: 1000000 | I10: 0 | J10: 0 | K10: 0 | L10: 0 | M10: 701873
B11: Total 2023 | C11: 112026337 | D11: 137765262 | E11: 16332187 | F11: 42245102 | G11: 18898080 | H11: 5696849 | I11: 4348949 | J11: 1677279 | K11: 38667 | L11: 38667 | M11: 36352207
B12: Total 2024 | C12: 23121913 | D12: 35347673 | E12: 75269181 | F12: 109065240 | G12: 109979614 | H12: 169098844 | I12: 106761879 | J12: 143873848 | K12: 135350270 | L12: 156749172 | M12: 126693119
B13: Pendientes | C13: 33103148 | D13: 34897138 | E13: 12846204 | F13: 10777832 | G13: 21820746 | H13: 5811361 | I13: 8809947 | J13: 19504055 | K13: 14522861 | L13: 38667 | M13: 25881682 | N13: 152384117
B14: Totales | C14: =SUM(C8:C13) -> 205615651 | D14: =SUM(D8:D13) -> 224465967 | E14: =SUM(E8:E13) -> 122330374 | F14: =SUM(F8:F13) -> 180618914 | G14: =SUM(G8:G13) -> 155720180 | H14: =SUM(H8:H13) -> 183387574 | I14: =SUM(I8:I13) -> 123694311 | J14: =SUM(J8:J13) -> 165055182 | ... N14: =SUM(N8:N13) -> 152384117

Sheet PAGOS
A1: Documento | B1: Clase de documento | C1: Texto de Cabecera | D1: Fecha de documento | E1: Fecha de contabilizacion | F1: Referencia | G1: Sociedad | H1: Norm. Pres. Ctas | I1: Posición | J1: Tipo de cuenta | K1: Cuenta | L1: Activo Fijo | M1: Sub Numero Activo Fijo | N1: Clase Movimiento AF | O1: Fecha Ref AA | P1: Indicador CME | Q1: Area Funcional | R1: Grafo | S1: Num Operacion | T1: Importe | U1: Moneda | V1: T/C | W1: Fecha Conversion | X1: Indicador impuestos | Y1: Tipo de Retencion | Z1: Ind de Retencion | AA1: Base Ret | AB1: Centro de coste | AC1: Centro de Beneficio | AD1: Elemento PEP | AE1: Orden CO | AF1: Fecha Valor | AG1: Banco Propio | AH1: ID de Cuenta | AI1: Asignacion | AJ1: Clave Ref 1 | AK1: Clave Ref 2 | AL1: Clave Ref 3 | AM1: Texto Posicion | AN1: Sociedad GL | AO1: EPS intervenida | AP1: Valor | AQ1: Mes
A2: 1 | B2: SA | C2: Reclasf. Reg | D2: 45314 | E2: 45314 | F2: Reclasf. Reg | G2: O003 | I2: 2 | J2: S | K2: 1533010002 | T2: 3499600 | U2: COP | AC2: O003001452 | AF2: 20230531 | AI2: 20230531 | AJ2: 8903030935 | AM2: PAGO DE PROV CAJA VALLE DEL CAUCA | AO2: 0 | AP2: =+ABS(T2) -> 3499600 | AQ2: =+MONTH(D2) -> 1
A3: 1 | B3: SA | C3: Pago Incap | D3: 45322 | E3: 45322 | F3: PAGO INCAP | G3: O003 | I3: 47 | J3: S | K3: 1533010002 | T3: -39028523 | U3: COP | AC3: O003001452 | AF3: 20240131 | AI3: 20240131 | AJ3: 8001309074 | AM3: PAGO DE PROV SALUD TOTAL EPS | AO3: 0 | AP3: =+ABS(T3) -> 39028523 | AQ3: =+MONTH(D3) -> 1
A4: 1 | B4: SA | C4: Pago Incap | D4: 45322 | E4: 45322 | F4: PAGO INCAP | G4: O003 | I4: 48 | J4: S | K4: 1533010002 | T4: -46914091 | U4: COP | AC4: O003001452 | AF4: 20240131 | AI4: 20240131 | AJ4: 8002514406 | AM4: PAGO INTERBANC EPS SANITAS S A | AO4: SANITAS | AP4: =+ABS(T4) -> 46914091 | AQ4: =+MONTH(D4) -> 1
A5: 1 | B5: SA | C5: Pago Incap | D5: 45322 | E5: 45322 | F5: PAGO INCAP | G5: O003 | I5: 49 | J5: S | K5: 1533010002 | T5: -3962995 | U5: COP | AC5: O003001452 | AF5: 20240131 | AI5: 20240131 | AJ5: 8050011572 | AM5: PAGO INTERBANC EPS SOS S A | AO5: 0 | AP5: =+ABS(T5) -> 3962995 | AQ5: =+MONTH(D5) -> 1
A6: 1 | B6: SA | C6: Pago Incap | D6: 45322 | E6: 45322 | F6: PAGO INCAP | G6: O003 | I6: 50 | J6: S | K6: 1533010002 | T6: -1121343 | U6: COP | AC6: O003001452 | AF6: 20240131 | AI6: 20240131 | AJ6: 8140003371 | AM6: PAGO INTERBANC EMSSANAR ENTIDA | AO6: EMSSANAR | AP6: =+ABS(T6) -> 1121343 | AQ6: =+MONTH(D6) -> 1
A7: 1 | B7: SA | C7: Pago Incap | D7: 45322 | E7: 45322 | F7: PAGO INCAP | G7: O003 | I7: 51 | J7: S | K7: 1533010002 | T7: -28827471 | U7: COP | AC7: O003001452 | AF7: 20240131 | AI7: 20240131 | AJ7: 8300035647 | AM7: PAGO INTERBANC EPS FAMISANAR S | AO7: FAMISANAR | AP7: =+ABS(T7) -> 28827471 | AQ7: =+MONTH(D7) -> 1
A8: 1 | B8: SA | C8: Pago Incap | D8: 45322 | E8: 45322 | F8: PAGO INCAP | G8: O003 | I8: 52 | J8: S | K8: 1533010002 | T8: -1342499 | U8: COP | AC8: O003001452 | AF8: 20240131 | AI8: 20240131 | AJ8: 8301138310 | AM8: PAGO DE PROV ALIANSALUD EPS | AO8: 0 | AP8: =+ABS(T8) -> 1342499 | AQ8: =+MONTH(D8) -> 1
A9: 1 | B9: SA | C9: Pago Incap | D9: 45322 | E9: 45322 | F9: PAGO INCAP | G9: O003 | I9: 53 | J9: S | K9: 1533010002 | T9: -15946683 | U9: COP | AC9: O003001452 | AF9: 20240131 | AI9: 20240131 | AJ9: 8600021839 | AM9: PAGO INTERBANC AXA COLPATRIA S | AO9: 0 | AP9: =+ABS(T9) -> 15946683 | AQ9: =+MONTH(D9) -> 1
A10: 1 | B10: SA | C10: Pago Incap | D10: 45322 | E10: 45322 | F10: PAGO INCAP | G10: O003 | I10: 54 | J10: S | K10: 1533010002 | T10: -8401543 | U10: COP | AC10: O003001452 | AF10: 20240131 | AI10: 20240131 | AJ10: 8600669427 | AM10: PAGO INTERBANC CAJA DE COMPENS | AO10: COMPENSAR | AP10: =+ABS(T10) -> 8401543 | AQ10: =+MONTH(D10) -> 1
A11: 1 | B11: SA | C11: Pago Incap | D11: 45322 | E11: 45322 | F11: PAGO INCAP | G11: O003 | I11: 55 | J11: S | K11: 1533010002 | T11: -40168602 | U11: COP | AC11: O003001452 | AF11: 20240131 | AI11: 20240131 | AJ11: 9001562642 | AM11: PAGO DE PROV NUEVA EPS S A | AO11: NUEVA E.P.S. | AP11: =+ABS(T11) -> 40168602 | AQ11: =+MONTH(D11) -> 1
A12: 1 | B12: SA | C12: Pago Incap | D12: 45322 | E12: 45322 | F12: PAGO INCAP | G12: O003 | I12: 56 | J12: S | K12: 1533010002 | T12: -3623546 | U12: COP | AC12: O003001452 | AF12: 20240131 | AI12: 20240131 | AJ12: 8000887022 | AM12: EPS SURA | AO12: EPS SURA (ANTES SUSALUD) | AP12: =+ABS(T12) -> 3623546 | AQ12: =+MONTH(D12) -> 1
A13: 1 | B13: SA | C13: Pago Incap | D13: 45322 | E13: 45322 | F13: PAGO INCAP | G13: O003 | I13: 83 | J13: S | K13: 1533010002 | T13: -5998997 | U13: COP | AC13: O003001452 | AF13: 20240131 | AI13: 20240131 | AJ13: 8903030935 | AM13: COMFENALCO VALLE | AO13: 0 | AP13: =+ABS(T13) -> 5998997 | AQ13: =+MONTH(D13) -> 1
A14: 1 | B14: SA | C14: Pago Incap | D14: 45322 | E14: 45322 | F14: PAGO INCAP | G14: O003 | I14: 84 | J14: S | K14: 1533010002 | T14: -9986886 | U14: COP | AC14: O003001452 | AF14: 20240131 | AI14: 20240131 | AJ14: 8903030935 | AM14: COMFENALCO VALLE | AO14: 0 | AP14: =+ABS(T14) -> 9986886 | AQ14: =+MONTH(D14) -> 1
A15: 1 | B15: SA | C15: Pago Incap | D15: 45322 | E15: 45322 | F15: PAGO INCAP | G15: O003 | I15: 85 | J15: S | K15: 1533010002 | T15: -292472 | U15: COP | AC15: O003001452 | AF15: 20240131 | AI15: 20240131 | AJ15: 8909049961 | AM15: EPM | AO15: 0 | AP15: =+ABS(T15) -> 292472 | AQ15: =+MONTH(D15) -> 1
A16: 1 | B16: SA | C16: Pago Incap | D16: 45351 | E16: 45351 | F16: PAGO INCAP | G16: O003 | I16: 52 | J16: S | K16: 1533010002 | T16: -42933257 | U16: COP | AC16: O003001452 | AF16: 20240229 | AI16: 20240229 | AJ16: 8000887022 | AM16: PAGO DE PROV EPS SURAMERICAN | AO16: EPS SURA (ANTES SUSALUD) | AP16: =+ABS(T16) -> 42933257 | AQ16: =+MONTH(D16) -> 2
A17: 1 | B17: SA | C17: Pago Incap | D17: 45351 | E17: 45351 | F17: PAGO INCAP | G17: O003 | I17: 53 | J17: S | K17: 1533010002 | T17: -2669518 | U17: COP | AC17: O003001452 | AF17: 20240229 | AI17: 20240229 | AJ17: 8001309074 | AM17: PAGO DE PROV SALUD TOTAL EPS | AO17: 0 | AP17: =+ABS(T17) -> 2669518 | AQ17: =+MONTH(D17) -> 2
A18: 1 | B18: SA | C18: Pago Incap | D18: 45351 | E18: 45351 | F18: PAGO INCAP | G18: O003 | I18: 54 | J18: S | K18: 1533010002 | T18: -71099032 | U18: COP | AC18: O003001452 | AF18: 20240229 | AI18: 20240229 | AJ18: 8002514406 | AM18: PAGO INTERBANC EPS SANITAS S A | AO18: SANITAS | AP18: =+ABS(T18) -> 71099032 | AQ18: =+MONTH(D18) -> 2
A19: 1 | B19: SA | C19: Pago Incap | D19: 45351 | E19: 45351 | F19: PAGO INCAP | G19: O003 | I19: 55 | J19: S | K19: 1533010002 | T19: -997911 | U19: COP | AC19: O003001452 | AF19: 20240229 | AI19: 20240229 | AJ19: 8050011572 | AM19: PAGO INTERBANC EPS SOS S A | AO19: 0 | AP19: =+ABS(T19) -> 997911 | AQ19: =+MONTH(D19) -> 2
A20: 1 | B20: SA | C20: Pago Incap | D20: 45351 | E20: 45351 | F20: PAGO INCAP | G20: O003 | I20: 56 | J20: S | K20: 1533010002 | T20: -38667 | U20: COP | AC20: O003001452 | AF20: 20240229 | AI20: 20240229 | AJ20: 8060083947 | AM20: PAGO INTERBANC MUTUAL SER EPS | AO20: 0 | AP20: =+ABS(T20) -> 38667 | AQ20: =+MONTH(D20) -> 2
A21: 1 | B21: SA | C21: Pago Incap | D21: 45351 | E21: 45351 | F21: PAGO INCAP | G21: O003 | I21: 57 | J21: S | K21: 1533010002 | T21: -2325361 | U21: COP | AC21: O003001452 | AF21: 20240229 | AI21: 20240229 | AJ21: 8140003371 | AM21: PAGO INTERBANC EMSSANAR ENTIDA | AO21: EMSSANAR | AP21: =+ABS(T21) -> 2325361 | AQ21: =+MONTH(D21) -> 2
A22: 1 | B22: SA | C22: Pago Incap | D22: 45351 | E22: 45351 | F22: PAGO INCAP | G22: O003 | I22: 58 | J22: S | K22: 1533010002 | T22: -17170822 | U22: COP | AC22: O003001452 | AF22: 20240229 | AI22: 20240229 | AJ22: 8300035647 | AM22: PAGO INTERBANC EPS FAMISANAR S | AO22: FAMISANAR | AP22: =+ABS(T22) -> 17170822 | AQ22: =+MONTH(D22) -> 2
A23: 1 | B23: SA | C23: Pago Incap | D23: 45351 | E23: 45351 | F23: PAGO INCAP | G23: O003 | I23: 59 | J23: S | K23: 1533010002 | T23: -16967412 | U23: COP | AC23: O003001452 | AF23: 20240229 | AI23: 20240229 | AJ23: 8301138310 | AM23: PAGO DE PROV ALIANSALUD EPS | AO23: 0 | AP23: =+ABS(T23) -> 16967412 | AQ23: =+MONTH(D23) -> 2
A24: 1 | B24: SA | C24: Pago Incap | D24: 45351 | E24: 45351 | F24: PAGO INCAP | G24: O003 | I24: 60 | J24: S | K24: 1533010002 | T24: -14573203 | U24: COP | AC24: O003001452 | AF24: 20240229 | AI24: 20240229 | AJ24: 8600021839 | AM24: PAGO INTERBANC AXA COLPATRIA S | AO24: 0 | AP24: =+ABS(T24) -> 14573203 | AQ24: =+MONTH(D24) -> 2
A25: 1 | B25: SA | C25: Pago Incap | D25: 45351 | E25: 45351 | F25: PAGO INCAP | G25: O003 | I25: 61 | J25: S | K25: 1533010002 | T25: -3510825 | U25: COP | AC25: O003001452 | AF25: 20240229 | AI25: 20240229 | AJ25: 8600669427 | AM25: PAGO INTERBANC CAJA DE COMPENS | AO25: COMPENSAR | AP25: =+ABS(T25) -> 3510825 | AQ25: =+MONTH(D25) -> 2
A26: 1 | B26: SA | C26: Pago Incap | D26: 45351 | E26: 45351 | F26: PAGO INCAP | G26: O003 | I26: 62 | J26: S | K26: 1533010002 | T26: -40155599 | U26: COP | AC26: O003001452 | AF26: 20240229 | AI26: 20240229 | AJ26: 9001562642 | AM26: PAGO DE PROV NUEVA EPS S A | AO26: NUEVA E.P.S. | AP26: =+ABS(T26) -> 40155599 | AQ26: =+MONTH(D26) -> 2
A27: 1 | B27: SA | C27: Pago Incap | D27: 45351 | E27: 45351 | F27: PAGO INCAP | G27: O003 | I27: 63 | J27: S | K27: 1533010002 | T27: -116001 | U27: COP | AC27: O003001452 | AF27: 20240229 | AI27: 20240229 | AJ27: 9002983729 | AM27: PAGO DE PROV CAPITAL SALUD E | AO27: 0 | AP27: =+ABS(T27) -> 116001 | AQ27: =+MONTH(D27) -> 2
A28: 1 | B28: SA | C28: Pago Incap | D28: 45351 | E28: 45351 | F28: PAGO INCAP | G28: O003 | I28: 64 | J28: S | K28: 1533010002 | T28: -1237344 | U28: COP | AC28: O003001452 | AF28: 20240229 | AI28: 20240229 | AJ28: 9006043500 | AM28: PAGO DE PROV AMA EPS S.A.S | AO28: 0 | AP28: =+ABS(T28) -> 1237344 | AQ28: =+MONTH(D28) -> 2
A29: 1 | B29: SA | C29: Pago Incap | D29: 45351 | E29: 45351 | F29: PAGO INCAP | G29: O003 | I29: 65 | J29: S | K29: 1533010002 | T29: -10671015 | U29: COP | AC29: O003001452 | AF29: 20240229 | AI29: 20240229 | AJ29: 9009142541 | AM29: PAGO INTERBANC FUNDACION SALUD | AO29: 0 | AP29: =+ABS(T29) -> 10671015 | AQ29: =+MONTH(D29) -> 2
A30: 4 | B30: SA | C30: Pago Incap | D30: 45382 | E30: 45382 | F30: PAGO INCAP | G30: O003 | I30: 237 | J30: S | K30: 1533010002 | T30: -12209087 | U30: COP | AC30: O003001452 | AF30: 20240331 | AI30: 20240331 | AJ30: 8000887022 | AM30: PAGO DE PROV EPS SURAMERICAN | AO30: EPS SURA (ANTES SUSALUD) | AP30: =+ABS(T30) -> 12209087 | AQ30: =+MONTH(D30) -> 3
A31: 4 | B31: SA | C31: Pago Incap | D31: 45382 | E31: 45382 | F31: PAGO INCAP | G31: O003 | I31: 238 | J31: S | K31: 1533010002 | T31: -6504524 | U31: COP | AC31: O003001452 | AF31: 20240331 | AI31: 20240331 | AJ31: 8001309074 | AM31: PAGO DE PROV SALUD TOTAL EPS | AO31: 0 | AP31: =+ABS(T31) -> 6504524 | AQ31: =+MONTH(D31) -> 3
A32: 4 | B32: SA | C32: Pago Incap | D32: 45382 | E32: 45382 | F32: PAGO INCAP | G32: O003 | I32: 239 | J32: S | K32: 1533010002 | T32: -3209334 | U32: COP | AC32: O003001452 | AF32: 20240331 | AI32: 20240331 | AJ32: 8002492410 | AM32: PAGO INTERBANC COOSALUD-ENTIDA | AO32: 0 | AP32: =+ABS(T32) -> 3209334 | AQ32: =+MONTH(D32) -> 3
A33: 4 | B33: SA | C33: Pago Incap | D33: 45382 | E33: 45382 | F33: PAGO INCAP | G33: O003 | I33: 240 | J33: S | K33: 1533010002 | T33: -15917110 | U33: COP | AC33: O003001452 | AF33: 20240331 | AI33: 20240331 | AJ33: 8002514406 | AM33: PAGO INTERBANC EPS SANITAS S A | AO33: SANITAS | AP33: =+ABS(T33) -> 15917110 | AQ33: =+MONTH(D33) -> 3
A34: 4 | B34: SA | C34: Pago Incap | D34: 45382 | E34: 45382 | F34: PAGO INCAP | G34: O003 | I34: 241 | J34: S | K34: 1533010002 | T34: -77334 | U34: COP | AC34: O003001452 | AF34: 20240331 | AI34: 20240331 | AJ34: 8050011572 | AM34: PAGO INTERBANC EPS SOS S A | AO34: 0 | AP34: =+ABS(T34) -> 77334 | AQ34: =+MONTH(D34) -> 3
A35: 4 | B35: SA | C35: Pago Incap | D35: 45382 | E35: 45382 | F35: PAGO INCAP | G35: O003 | I35: 242 | J35: S | K35: 1533010002 | T35: -212001 | U35: COP | AC35: O003001452 | AF35: 20240331 | AI35: 20240331 | AJ35: 8060083947 | AM35: PAGO INTERBANC MUTUAL SER EPS | AO35: 0 | AP35: =+ABS(T35) -> 212001 | AQ35: =+MONTH(D35) -> 3
A36: 4 | B36: SA | C36: Pago Incap | D36: 45382 | E36: 45382 | F36: PAGO INCAP | G36: O003 | I36: 243 | J36: S | K36: 1533010002 | T36: -16862650 | U36: COP | AC36: O003001452 | AF36: 20240331 | AI36: 20240331 | AJ36: 8300035647 | AM36: PAGO INTERBANC EPS FAMISANAR S | AO36: FAMISANAR | AP36: =+ABS(T36) -> 16862650 | AQ36: =+MONTH(D36) -> 3
A37: 4 | B37: SA | C37: Pago Incap | D37: 45382 | E37: 45382 | F37: PAGO INCAP | G37: O003 | I37: 244 | J37: S | K37: 1533010002 | T37: -22887098 | U37: COP | AC37: O003001452 | AF37: 20240331 | AI37: 20240331 | AJ37: 8301138310 | AM37: PAGO DE PROV ALIANSALUD EPS | AO37: 0 | AP37: =+ABS(T37) -> 22887098 | AQ37: =+MONTH(D37) -> 3
A38: 4 | B38: SA | C38: Pago Incap | D38: 45382 | E38: 45382 | F38: PAGO INCAP | G38: O003 | I38: 245 | J38: S | K38: 1533010002 | T38: -14001696 | U38: COP | AC38: O003001452 | AF38: 20240331 | AI38: 20240331 | AJ38: 8600021839 | AM38: PAGO INTERBANC AXA COLPATRIA S | AO38: 0 | AP38: =+ABS(T38) -> 14001696 | AQ38: =+MONTH(D38) -> 3
A39: 4 | B39: SA | C39: Pago Incap | D39: 45382 | E39: 45382 | F39: PAGO INCAP | G39: O003 | I39: 246 | J39: S | K39: 1533010002 | T39: -8704906 | U39: COP | AC39: O003001452 | AF39: 20240331 | AI39: 20240331 | AJ39: 8600669427 | AM39: PAGO INTERBANC CAJA DE COMPENS | AO39: COMPENSAR | AP39: =+ABS(T39) -> 8704906 | AQ39: =+MONTH(D39) -> 3
A40: 4 | B40: SA | C40: Pago Incap | D40: 45382 | E40: 45382 | F40: PAGO INCAP | G40: O003 | I40: 247 | J40: S | K40: 1533010002 | T40: -21704777 | U40: COP | AC40: O003001452 | AF40: 20240331 | AI40: 20240331 | AJ40: 9001562642 | AM40: PAGO DE PROV NUEVA EPS S A | AO40: NUEVA E.P.S. | AP40: =+ABS(T40) -> 21704777 | AQ40: =+MONTH(D40) -> 3
A41: 4 | B41: SA | C41: Pago Incap | D41: 45382 | E41: 45382 | F41: PAGO INCAP | G41: O003 | I41: 248 | J41: S | K41: 1533010002 | T41: -39857 | U41: COP | AC41: O003001452 | AF41: 20240331 | AI41: 20240331 | AJ41: 9009142541 | AM41: PAGO INTERBANC FUNDACION SALUD | AO41: 0 | AP41: =+ABS(T41) -> 39857 | AQ41: =+MONTH(D41) -> 3
A42: 7 | B42: SA | C42: Pago Incap | D42: 45382 | E42: 45382 | F42: PAGO INCAP | G42: O003 | I42: 257 | J42: S | K42: 1533010002 | T42: 3623546 | U42: COP | AC42: O003001452 | AF42: 20240331 | AI42: 20240331 | AJ42: 8000887022 | AM42: EPS SURA | AO42: EPS SURA (ANTES SUSALUD) | AP42: =+ABS(T42) -> 3623546 | AQ42: =+MONTH(D42) -> 3
A43: 7 | B43: SA | C43: Pago Incap | D43: 45382 | E43: 45382 | F43: PAGO INCAP | G43: O003 | I43: 258 | J43: S | K43: 1533010002 | T43: 232000 | U43: COP | AC43: O003001452 | AF43: 20240331 | AI43: 20240331 | AJ43: 8600669427 | AM43: PAGO INTERBANC CAJA DE COMPENS | AO43: COMPENSAR | AP43: =+ABS(T43) -> 232000 | AQ43: =+MONTH(D43) -> 3
A44: 7 | B44: SA | C44: Pago Incap | D44: 45382 | E44: 45382 | F44: PAGO INCAP | G44: O003 | I44: 259 | J44: S | K44: 1533010002 | T44: 256134 | U44: COP | AC44: O003001452 | AF44: 20240331 | AI44: 20240331 | AJ44: 8600021839 | AM44: PAGO INTERBANC AXA COLPATRIA S | AO44: 0 | AP44: =+ABS(T44) -> 256134 | AQ44: =+MONTH(D44) -> 3
A45: 7 | B45: SA | C45: Pago Incap | D45: 45382 | E45: 45382 | F45: PAGO INCAP | G45: O003 | I45: 260 | J45: S | K45: 1533010002 | T45: 5998997 | U45: COP | AC45: O003001452 | AF45: 20240331 | AI45: 20240331 | AJ45: 8903030935 | AM45: COMFENALCO VALLE | AO45: 0 | AP45: =+ABS(T45) -> 5998997 | AQ45: =+MONTH(D45) -> 3
A46: 2 | B46: SA | C46: Pago Incap | D46: 45412 | E46: 45412 | F46: PAGO INCAP | G46: O003 | I46: 91 | J46: S | K46: 1533010002 | T46: -38885230 | U46: COP | AC46: O003001452 | AF46: 20240430 | AI46: 20240430 | AJ46: 8000887022 | AM46: PAGO DE PROV EPS SURAMERICAN | AO46: EPS SURA (ANTES SUSALUD) | AP46: =+ABS(T46) -> 38885230 | AQ46: =+MONTH(D46) -> 4
A47: 2 | B47: SA | C47: Pago Incap | D47: 45412 | E47: 45412 | F47: PAGO INCAP | G47: O003 | I47: 92 | J47: S | K47: 1533010002 | T47: -28502131 | U47: COP | AC47: O003001452 | AF47: 20240430 | AI47: 20240430 | AJ47: 8001309074 | AM47: PAGO DE PROV SALUD TOTAL EPS | AO47: 0 | AP47: =+ABS(T47) -> 28502131 | AQ47: =+MONTH(D47) -> 4
A48: 2 | B48: SA | C48: Pago Incap | D48: 45412 | E48: 45412 | F48: PAGO INCAP | G48: O003 | I48: 93 | J48: S | K48: 1533010002 | T48: -2226672 | U48: COP | AC48: O003001452 | AF48: 20240430 | AI48: 20240430 | AJ48: 8002492410 | AM48: PAGO INTERBANC COOSALUD-ENTIDA | AO48: 0 | AP48: =+ABS(T48) -> 2226672 | AQ48: =+MONTH(D48) -> 4
A49: 2 | B49: SA | C49: Pago Incap | D49: 45412 | E49: 45412 | F49: PAGO INCAP | G49: O003 | I49: 94 | J49: S | K49: 1533010002 | T49: -32810713 | U49: COP | AC49: O003001452 | AF49: 20240430 | AI49: 20240430 | AJ49: 8002514406 | AM49: PAGO INTERBANC EPS SANITAS S A | AO49: SANITAS | AP49: =+ABS(T49) -> 32810713 | AQ49: =+MONTH(D49) -> 4
A50: 2 | B50: SA | C50: Pago Incap | D50: 45412 | E50: 45412 | F50: PAGO INCAP | G50: O003 | I50: 95 | J50: S | K50: 1533010002 | T50: -886770 | U50: COP | AC50: O003001452 | AF50: 20240430 | AI50: 20240430 | AJ50: 8050011572 | AM50: PAGO INTERBANC EPS SOS S A | AO50: 0 | AP50: =+ABS(T50) -> 886770 | AQ50: =+MONTH(D50) -> 4
A51: 2 | B51: SA | C51: Pago Incap | D51: 45412 | E51: 45412 | F51: PAGO INCAP | G51: O003 | I51: 96 | J51: S | K51: 1533010002 | T51: -705335 | U51: COP | AC51: O003001452 | AF51: 20240430 | AI51: 20240430 | AJ51: 8060083947 | AM51: PAGO INTERBANC MUTUAL SER EPS | AO51: 0 | AP51: =+ABS(T51) -> 705335 | AQ51: =+MONTH(D51) -> 4
A52: 2 | B52: SA | C52: Pago Incap | D52: 45412 | E52: 45412 | F52: PAGO INCAP | G52: O003 | I52: 97 | J52: S | K52: 1533010002 | T52: -86668 | U52: COP | AC52: O003001452 | AF52: 20240430 | AI52: 20240430 | AJ52: 8140003371 | AM52: PAGO INTERBANC EMSSANAR ENTIDA | AO52: EMSSANAR | AP52: =+ABS(T52) -> 86668 | AQ52: =+MONTH(D52) -> 4
A53: 2 | B53: SA | C53: Pago Incap | D53: 45412 | E53: 45412 | F53: PAGO INCAP | G53: O003 | I53: 98 | J53: S | K53: 1533010002 | T53: -18386363 | U53: COP | AC53: O003001452 | AF53: 20240430 | AI53: 20240430 | AJ53: 8300035647 | AM53: PAGO INTERBANC EPS FAMISANAR S | AO53: FAMISANAR | AP53: =+ABS(T53) -> 18386363 | AQ53: =+MONTH(D53) -> 4
A54: 2 | B54: SA | C54: Pago Incap | D54: 45412 | E54: 45412 | F54: PAGO INCAP | G54: O003 | I54: 99 | J54: S | K54: 1533010002 | T54: -3620679 | U54: COP | AC54: O003001452 | AF54: 20240430 | AI54: 20240430 | AJ54: 8301138310 | AM54: PAGO DE PROV ALIANSALUD EPS | AO54: 0 | AP54: =+ABS(T54) -> 3620679 | AQ54: =+MONTH(D54) -> 4
A55: 2 | B55: SA | C55: Pago Incap | D55: 45412 | E55: 45412 | F55: PAGO INCAP | G55: O003 | I55: 100 | J55: S | K55: 1533010002 | T55: -7845825 | U55: COP | AC55: O003001452 | AF55: 20240430 | AI55: 20240430 | AJ55: 8600021839 | AM55: PAGO INTERBANC AXA COLPATRIA S | AO55: 0 | AP55: =+ABS(T55) -> 7845825 | AQ55: =+MONTH(D55) -> 4
A56: 2 | B56: SA | C56: Pago Incap | D56: 45412 | E56: 45412 | F56: PAGO INCAP | G56: O003 | I56: 101 | J56: S | K56: 1533010002 | T56: -8626224 | U56: COP | AC56: O003001452 | AF56: 20240430 | AI56: 20240430 | AJ56: 8600669427 | AM56: PAGO INTERBANC CAJA DE COMPENS | AO56: COMPENSAR | AP56: =+ABS(T56) -> 8626224 | AQ56: =+MONTH(D56) -> 4
A57: 2 | B57: SA | C57: Pago Incap | D57: 45412 | E57: 45412 | F57: PAGO INCAP | G57: O003 | I57: 102 | J57: S | K57: 1533010002 | T57: -19238721 | U57: COP | AC57: O003001452 | AF57: 20240430 | AI57: 20240430 | AJ57: 8903030935 | AM57: COMFENALCO VALLE | AO57: 0 | AP57: =+ABS(T57) -> 19238721 | AQ57: =+MONTH(D57) -> 4
A58: 2 | B58: SA | C58: Pago Incap | D58: 45412 | E58: 45412 | F58: PAGO INCAP | G58: O003 | I58: 103 | J58: S | K58: 1533010002 | T58: -18797583 | U58: COP | AC58: O003001452 | AF58: 20240430 | AI58: 20240430 | AJ58: 9001562642 | AM58: PAGO DE PROV NUEVA EPS S A | AO58: NUEVA E.P.S. | AP58: =+ABS(T58) -> 18797583 | AQ58: =+MONTH(D58) -> 4
A59: 1 | B59: SA | C59: Pago Incap | D59: 45443 | E59: 45443 | F59: PAGO INCAP | G59: O003 | I59: 66 | J59: S | K59: 1533010002 | T59: -16590832 | U59: COP | AC59: O003001452 | AF59: 20240531 | AI59: 20240531 | AJ59: 8000887022 | AM59: PAGO DE PROV EPS SURAMERICAN | AO59: EPS SURA (ANTES SUSALUD) | AP59: =+ABS(T59) -> 16590832 | AQ59: =+MONTH(D59) -> 5
A60: 1 | B60: SA | C60: Pago Incap | D60: 45443 | E60: 45443 | F60: PAGO INCAP | G60: O003 | I60: 67 | J60: S | K60: 1533010002 | T60: -6757008 | U60: COP | AC60: O003001452 | AF60: 20240531 | AI60: 20240531 | AJ60: 8001309074 | AM60: PAGO DE PROV SALUD TOTAL EPS | AO60: 0 | AP60: =+ABS(T60) -> 6757008 | AQ60: =+MONTH(D60) -> 5
A61: 1 | B61: SA | C61: Pago Incap | D61: 45443 | E61: 45443 | F61: PAGO INCAP | G61: O003 | I61: 68 | J61: S | K61: 1533010002 | T61: -4278379 | U61: COP | AC61: O003001452 | AF61: 20240531 | AI61: 20240531 | AJ61: 8002492410 | AM61: PAGO INTERBANC COOSALUD-ENTIDA | AO61: 0 | AP61: =+ABS(T61) -> 4278379 | AQ61: =+MONTH(D61) -> 5
A62: 1 | B62: SA | C62: Pago Incap | D62: 45443 | E62: 45443 | F62: PAGO INCAP | G62: O003 | I62: 69 | J62: S | K62: 1533010002 | T62: -48757908 | U62: COP | AC62: O003001452 | AF62: 20240531 | AI62: 20240531 | AJ62: 8002514406 | AM62: PAGO INTERBANC EPS SANITAS S A | AO62: SANITAS | AP62: =+ABS(T62) -> 48757908 | AQ62: =+MONTH(D62) -> 5
A63: 1 | B63: SA | C63: Pago Incap | D63: 45443 | E63: 45443 | F63: PAGO INCAP | G63: O003 | I63: 70 | J63: S | K63: 1533010002 | T63: -4915334 | U63: COP | AC63: O003001452 | AF63: 20240531 | AI63: 20240531 | AJ63: 8050011572 | AM63: PAGO INTERBANC EPS SOS S A | AO63: 0 | AP63: =+ABS(T63) -> 4915334 | AQ63: =+MONTH(D63) -> 5
A64: 1 | B64: SA | C64: Pago Incap | D64: 45443 | E64: 45443 | F64: PAGO INCAP | G64: O003 | I64: 71 | J64: S | K64: 1533010002 | T64: -43334 | U64: COP | AC64: O003001452 | AF64: 20240531 | AI64: 20240531 | AJ64: 8060083947 | AM64: PAGO DE PROV ASOCIACION MUTU | AO64: 0 | AP64: =+ABS(T64) -> 43334 | AQ64: =+MONTH(D64) -> 5
A65: 1 | B65: SA | C65: Pago Incap | D65: 45443 | E65: 45443 | F65: PAGO INCAP | G65: O003 | I65: 72 | J65: S | K65: 1533010002 | T65: -1560012 | U65: COP | AC65: O003001452 | AF65: 20240531 | AI65: 20240531 | AJ65: 8060083947 | AM65: PAGO INTERBANC MUTUAL SER EPS | AO65: 0 | AP65: =+ABS(T65) -> 1560012 | AQ65: =+MONTH(D65) -> 5
A66: 1 | B66: SA | C66: Pago Incap | D66: 45443 | E66: 45443 | F66: PAGO INCAP | G66: O003 | I66: 73 | J66: S | K66: 1533010002 | T66: -1473356 | U66: COP | AC66: O003001452 | AF66: 20240531 | AI66: 20240531 | AJ66: 8140003371 | AM66: PAGO INTERBANC EMSSANAR ENTIDA | AO66: EMSSANAR | AP66: =+ABS(T66) -> 1473356 | AQ66: =+MONTH(D66) -> 5
A67: 1 | B67: SA | C67: Pago Incap | D67: 45443 | E67: 45443 | F67: PAGO INCAP | G67: O003 | I67: 74 | J67: S | K67: 1533010002 | T67: -11480473 | U67: COP | AC67: O003001452 | AF67: 20240531 | AI67: 20240531 | AJ67: 8300035647 | AM67: PAGO INTERBANC EPS FAMISANAR S | AO67: FAMISANAR | AP67: =+ABS(T67) -> 11480473 | AQ67: =+MONTH(D67) -> 5
A68: 1 | B68: SA | C68: Pago Incap | D68: 45443 | E68: 45443 | F68: PAGO INCAP | G68: O003 | I68: 75 | J68: S | K68: 1533010002 | T68: -6094960 | U68: COP | AC68: O003001452 | AF68: 20240531 | AI68: 20240531 | AJ68: 8301138310 | AM68: PAGO DE PROV ALIANSALUD EPS | AO68: 0 | AP68: =+ABS(T68) -> 6094960 | AQ68: =+MONTH(D68) -> 5
A69: 1 | B69: SA | C69: Pago Incap | D69: 45443 | E69: 45443 | F69: PAGO INCAP | G69: O003 | I69: 76 | J69: S | K69: 1533010002 | T69: -20904576 | U69: COP | AC69: O003001452 | AF69: 20240531 | AI69: 20240531 | AJ69: 8600021839 | AM69: PAGO INTERBANC AXA COLPATRIA S | AO69: 0 | AP69: =+ABS(T69) -> 20904576 | AQ69: =+MONTH(D69) -> 5
A70: 1 | B70: SA | C70: Pago Incap | D70: 45443 | E70: 45443 | F70: PAGO INCAP | G70: O003 | I70: 77 | J70: S | K70: 1533010002 | T70: -4130041 | U70: COP | AC70: O003001452 | AF70: 20240531 | AI70: 20240531 | AJ70: 8600669427 | AM70: PAGO INTERBANC CAJA DE COMPENS | AO70: COMPENSAR | AP70: =+ABS(T70) -> 4130041 | AQ70: =+MONTH(D70) -> 5
A71: 1 | B71: SA | C71: Pago Incap | D71: 45443 | E71: 45443 | F71: PAGO INCAP | G71: O003 | I71: 78 | J71: S | K71: 1533010002 | T71: -28733967 | U71: COP | AC71: O003001452 | AF71: 20240531 | AI71: 20240531 | AJ71: 9001562642 | AM71: PAGO DE PROV NUEVA EPS S A | AO71: NUEVA E.P.S. | AP71: =+ABS(T71) -> 28733967 | AQ71: =+MONTH(D71) -> 5
A72: 1 | B72: SA | C72: Pago Incap | D72: 45473 | E72: 45473 | F72: PAGO INCAP | G72: O003 | I72: 54 | J72: S | K72: 1533010002 | T72: -36563373 | U72: COP | AC72: O003001452 | AF72: 20240630 | AI72: 20240630 | AJ72: 8000887022 | AM72: PAGO DE PROV EPS SURAMERICAN | AO72: EPS SURA (ANTES SUSALUD) | AP72: =+ABS(T72) -> 36563373 | AQ72: =+MONTH(D72) -> 6
A73: 1 | B73: SA | C73: Pago Incap | D73: 45473 | E73: 45473 | F73: PAGO INCAP | G73: O003 | I73: 55 | J73: S | K73: 1533010002 | T73: -1346004 | U73: COP | AC73: O003001452 | AF73: 20240630 | AI73: 20240630 | AJ73: 8001309074 | AM73: PAGO DE PROV SALUD TOTAL EPS | AO73: 0 | AP73: =+ABS(T73) -> 1346004 | AQ73: =+MONTH(D73) -> 6
A74: 1 | B74: SA | C74: Pago Incap | D74: 45473 | E74: 45473 | F74: PAGO INCAP | G74: O003 | I74: 56 | J74: S | K74: 1533010002 | T74: -1690002 | U74: COP | AC74: O003001452 | AF74: 20240630 | AI74: 20240630 | AJ74: 8002492410 | AM74: PAGO INTERBANC COOSALUD-ENTIDA | AO74: 0 | AP74: =+ABS(T74) -> 1690002 | AQ74: =+MONTH(D74) -> 6
A75: 1 | B75: SA | C75: Pago Incap | D75: 45473 | E75: 45473 | F75: PAGO INCAP | G75: O003 | I75: 57 | J75: S | K75: 1533010002 | T75: -73300637 | U75: COP | AC75: O003001452 | AF75: 20240630 | AI75: 20240630 | AJ75: 8002514406 | AM75: PAGO INTERBANC EPS SANITAS S A | AO75: SANITAS | AP75: =+ABS(T75) -> 73300637 | AQ75: =+MONTH(D75) -> 6
A76: 1 | B76: SA | C76: Pago Incap | D76: 45473 | E76: 45473 | F76: PAGO INCAP | G76: O003 | I76: 58 | J76: S | K76: 1533010002 | T76: -140871 | U76: COP | AC76: O003001452 | AF76: 20240630 | AI76: 20240630 | AJ76: 8050011572 | AM76: PAGO INTERBANC EPS SOS S A | AO76: 0 | AP76: =+ABS(T76) -> 140871 | AQ76: =+MONTH(D76) -> 6
A77: 1 | B77: SA | C77: Pago Incap | D77: 45473 | E77: 45473 | F77: PAGO INCAP | G77: O003 | I77: 59 | J77: S | K77: 1533010002 | T77: -130000 | U77: COP | AC77: O003001452 | AF77: 20240630 | AI77: 20240630 | AJ77: 8060083947 | AM77: PAGO DE PROV ASOCIACION MUTU | AO77: 0 | AP77: =+ABS(T77) -> 130000 | AQ77: =+MONTH(D77) -> 6
A78: 1 | B78: SA | C78: Pago Incap | D78: 45473 | E78: 45473 | F78: PAGO INCAP | G78: O003 | I78: 60 | J78: S | K78: 1533010002 | T78: -323334 | U78: COP | AC78: O003001452 | AF78: 20240630 | AI78: 20240630 | AJ78: 8060083947 | AM78: PAGO INTERBANC MUTUAL SER EPS | AO78: 0 | AP78: =+ABS(T78) -> 323334 | AQ78: =+MONTH(D78) -> 6
A79: 1 | B79: SA | C79: Pago Incap | D79: 45473 | E79: 45473 | F79: PAGO INCAP | G79: O003 | I79: 61 | J79: S | K79: 1533010002 | T79: -216670 | U79: COP | AC79: O003001452 | AF79: 20240630 | AI79: 20240630 | AJ79: 8140003371 | AM79: PAGO INTERBANC EMSSANAR EMPRES | AO79: EMSSANAR | AP79: =+ABS(T79) -> 216670 | AQ79: =+MONTH(D79) -> 6
A80: 1 | B80: SA | C80: Pago Incap | D80: 45473 | E80: 45473 | F80: PAGO INCAP | G80: O003 | I80: 62 | J80: S | K80: 1533010002 | T80: -13305834 | U80: COP | AC80: O003001452 | AF80: 20240630 | AI80: 20240630 | AJ80: 8300035647 | AM80: PAGO INTERBANC EPS FAMISANAR S | AO80: FAMISANAR | AP80: =+ABS(T80) -> 13305834 | AQ80: =+MONTH(D80) -> 6
A81: 1 | B81: SA | C81: Pago Incap | D81: 45473 | E81: 45473 | F81: PAGO INCAP | G81: O003 | I81: 63 | J81: S | K81: 1533010002 | T81: -5643423 | U81: COP | AC81: O003001452 | AF81: 20240630 | AI81: 20240630 | AJ81: 8301138310 | AM81: PAGO DE PROV ALIANSALUD EPS | AO81: 0 | AP81: =+ABS(T81) -> 5643423 | AQ81: =+MONTH(D81) -> 6
A82: 1 | B82: SA | C82: Pago Incap | D82: 45473 | E82: 45473 | F82: PAGO INCAP | G82: O003 | I82: 64 | J82: S | K82: 1533010002 | T82: -8352907 | U82: COP | AC82: O003001452 | AF82: 20240630 | AI82: 20240630 | AJ82: 8600021839 | AM82: PAGO INTERBANC AXA COLPATRIA S | AO82: 0 | AP82: =+ABS(T82) -> 8352907 | AQ82: =+MONTH(D82) -> 6
A83: 1 | B83: SA | C83: Pago Incap | D83: 45473 | E83: 45473 | F83: PAGO INCAP | G83: O003 | I83: 65 | J83: S | K83: 1533010002 | T83: -2956030 | U83: COP | AC83: O003001452 | AF83: 20240630 | AI83: 20240630 | AJ83: 8600669427 | AM83: PAGO INTERBANC CAJA DE COMPENS | AO83: COMPENSAR | AP83: =+ABS(T83) -> 2956030 | AQ83: =+MONTH(D83) -> 6
A84: 1 | B84: SA | C84: Pago Incap | D84: 45473 | E84: 45473 | F84: PAGO INCAP | G84: O003 | I84: 66 | J84: S | K84: 1533010002 | T84: -39516027 | U84: COP | AC84: O003001452 | AF84: 20240630 | AI84: 20240630 | AJ84: 9001562642 | AM84: PAGO DE PROV NUEVA EPS S A | AO84: NUEVA E.P.S. | AP84: =+ABS(T84) -> 39516027 | AQ84: =+MONTH(D84) -> 6
A85: 1 | B85: SA | C85: Pago Incap | D85: 45504 | E85: 45504 | F85: PAGO INCAP | G85: O003 | I85: 57 | J85: S | K85: 1533010002 | T85: -38074012 | U85: COP | AC85: O003001452 | AF85: 20240731 | AI85: 20240731 | AJ85: 8000887022 | AM85: PAGO DE PROV EPS SURAMERICAN | AO85: EPS SURA (ANTES SUSALUD) | AP85: =+ABS(T85) -> 38074012 | AQ85: =+MONTH(D85) -> 7
A86: 1 | B86: SA | C86: Pago Incap | D86: 45504 | E86: 45504 | F86: PAGO INCAP | G86: O003 | I86: 58 | J86: S | K86: 1533010002 | T86: -12766756 | U86: COP | AC86: O003001452 | AF86: 20240731 | AI86: 20240731 | AJ86: 8001309074 | AM86: PAGO DE PROV SALUD TOTAL EPS | AO86: 0 | AP86: =+ABS(T86) -> 12766756 | AQ86: =+MONTH(D86) -> 7
A87: 1 | B87: SA | C87: Pago Incap | D87: 45504 | E87: 45504 | F87: PAGO INCAP | G87: O003 | I87: 59 | J87: S | K87: 1533010002 | T87: -2296669 | U87: COP | AC87: O003001452 | AF87: 20240731 | AI87: 20240731 | AJ87: 8002492410 | AM87: PAGO INTERBANC COOSALUD-ENTIDA | AO87: 0 | AP87: =+ABS(T87) -> 2296669 | AQ87: =+MONTH(D87) -> 7
A88: 1 | B88: SA | C88: Pago Incap | D88: 45504 | E88: 45504 | F88: PAGO INCAP | G88: O003 | I88: 60 | J88: S | K88: 1533010002 | T88: -28671155 | U88: COP | AC88: O003001452 | AF88: 20240731 | AI88: 20240731 | AJ88: 8002514406 | AM88: PAGO INTERBANC EPS SANITAS S A | AO88: SANITAS | AP88: =+ABS(T88) -> 28671155 | AQ88: =+MONTH(D88) -> 7
A89: 1 | B89: SA | C89: Pago Incap | D89: 45504 | E89: 45504 | F89: PAGO INCAP | G89: O003 | I89: 61 | J89: S | K89: 1533010002 | T89: -362973 | U89: COP | AC89: O003001452 | AF89: 20240731 | AI89: 20240731 | AJ89: 8050011572 | AM89: PAGO INTERBANC EPS SOS S A | AO89: 0 | AP89: =+ABS(T89) -> 362973 | AQ89: =+MONTH(D89) -> 7
A90: 1 | B90: SA | C90: Pago Incap | D90: 45504 | E90: 45504 | F90: PAGO INCAP | G90: O003 | I90: 62 | J90: S | K90: 1533010002 | T90: -866680 | U90: COP | AC90: O003001452 | AF90: 20240731 | AI90: 20240731 | AJ90: 8140003371 | AM90: PAGO INTERBANC EMSSANAR EMPRES | AO90: EMSSANAR | AP90: =+ABS(T90) -> 866680 | AQ90: =+MONTH(D90) -> 7
A91: 1 | B91: SA | C91: Pago Incap | D91: 45504 | E91: 45504 | F91: PAGO INCAP | G91: O003 | I91: 63 | J91: S | K91: 1533010002 | T91: -3410899 | U91: COP | AC91: O003001452 | AF91: 20240731 | AI91: 20240731 | AJ91: 8301138310 | AM91: PAGO DE PROV ALIANSALUD EPS | AO91: 0 | AP91: =+ABS(T91) -> 3410899 | AQ91: =+MONTH(D91) -> 7
A92: 1 | B92: SA | C92: Pago Incap | D92: 45504 | E92: 45504 | F92: PAGO INCAP | G92: O003 | I92: 64 | J92: S | K92: 1533010002 | T92: -10504478 | U92: COP | AC92: O003001452 | AF92: 20240731 | AI92: 20240731 | AJ92: 8600021839 | AM92: PAGO INTERBANC AXA COLPATRIA S | AO92: 0 | AP92: =+ABS(T92) -> 10504478 | AQ92: =+MONTH(D92) -> 7
A93: 1 | B93: SA | C93: Pago Incap | D93: 45504 | E93: 45504 | F93: PAGO INCAP | G93: O003 | I93: 65 | J93: S | K93: 1533010002 | T93: -10427008 | U93: COP | AC93: O003001452 | AF93: 20240731 | AI93: 20240731 | AJ93: 8600669427 | AM93: PAGO INTERBANC CAJA DE COMPENS | AO93: COMPENSAR | AP93: =+ABS(T93) -> 10427008 | AQ93: =+MONTH(D93) -> 7
A94: 1 | B94: SA | C94: Pago Incap | D94: 45504 | E94: 45504 | F94: PAGO INCAP | G94: O003 | I94: 66 | J94: S | K94: 1533010002 | T94: -12119203 | U94: COP | AC94: O003001452 | AF94: 20240731 | AI94: 20240731 | AJ94: 9001562642 | AM94: PAGO DE PROV NUEVA EPS S A | AO94: NUEVA E.P.S. | AP94: =+ABS(T94) -> 12119203 | AQ94: =+MONTH(D94) -> 7
A95: 1 | B95: SA | C95: Pago Incap | D95: 45504 | E95: 45504 | F95: PAGO INCAP | G95: O003 | I95: 67 | J95: S | K95: 1533010002 | T95: -812000 | U95: COP | AC95: O003001452 | AF95: 20240731 | AI95: 20240731 | AJ95: 9002983729 | AM95: PAGO DE PROV CAPITAL SALUD E | AO95: 0 | AP95: =+ABS(T95) -> 812000 | AQ95: =+MONTH(D95) -> 7
A96: 1 | B96: SA | C96: Pago Incap | D96: 45504 | E96: 45504 | F96: PAGO INCAP | G96: O003 | I96: 68 | J96: S | K96: 1533010002 | T96: -43334 | U96: COP | AC96: O003001452 | AF96: 20240731 | AI96: 20240731 | AJ96: 9006043500 | AM96: PAGO DE PROV AMA EPS S.A.S | AO96: 0 | AP96: =+ABS(T96) -> 43334 | AQ96: =+MONTH(D96) -> 7
A97: 1 | B97: SA | C97: Pago Incap | D97: 45535 | E97: 45535 | F97: PAGO INCAP | G97: O003 | I97: 51 | J97: S | K97: 1533010002 | T97: -53941400 | U97: COP | AC97: O003001452 | AF97: 20240831 | AI97: 20240831 | AJ97: 8000887022 | AM97: PAGO DE PROV EPS SURAMERICAN | AO97: EPS SURA (ANTES SUSALUD) | AP97: =+ABS(T97) -> 53941400 | AQ97: =+MONTH(D97) -> 8
A98: 1 | B98: SA | C98: Pago Incap | D98: 45535 | E98: 45535 | F98: PAGO INCAP | G98: O003 | I98: 52 | J98: S | K98: 1533010002 | T98: -2598016 | U98: COP | AC98: O003001452 | AF98: 20240831 | AI98: 20240831 | AJ98: 8001309074 | AM98: PAGO DE PROV SALUD TOTAL EPS | AO98: 0 | AP98: =+ABS(T98) -> 2598016 | AQ98: =+MONTH(D98) -> 8
A99: 1 | B99: SA | C99: Pago Incap | D99: 45535 | E99: 45535 | F99: PAGO INCAP | G99: O003 | I99: 53 | J99: S | K99: 1533010002 | T99: -650000 | U99: COP | AC99: O003001452 | AF99: 20240831 | AI99: 20240831 | AJ99: 8002492410 | AM99: PAGO INTERBANC COOSALUD-ENTIDA | AO99: 0 | AP99: =+ABS(T99) -> 650000 | AQ99: =+MONTH(D99) -> 8
A100: 1 | B100: SA | C100: Pago Incap | D100: 45535 | E100: 45535 | F100: PAGO INCAP | G100: O003 | I100: 54 | J100: S | K100: 1533010002 | T100: -39791220 | U100: COP | AC100: O003001452 | AF100: 20240831 | AI100: 20240831 | AJ100: 8002514406 | AM100: PAGO INTERBANC EPS SANITAS S A | AO100: SANITAS | AP100: =+ABS(T100) -> 39791220 | AQ100: =+MONTH(D100) -> 8
...
